Workbook

Sheet Finanzen_Overall
B1: ALT | C1: Heute mit Zins | D1: Heute mit Wohnung | E1: Heute mit Wohnung inkl. Downgrade | F1: Heute mit Wohnung ohne 40 | G1: Haus mit 40 | H1: Haus mit 40 mit Einschnitt | I1: Haus mit 40 mit Radikal Einschnitt | J1: Haus ohne 40 | K1: Haus ohne 40 mit Einschnitt | L1: Haus ohne 40 mit Radikal Einschnitt | M1: Heute mit Wohnung und AVD
A2: Income | B2: 5650 | C2: 5930 | D2: 5930 | E2: 5930 | F2: 5230 | G2: 5600 | H2: 5600 | I2: 5600 | J2: 5000 | K2: 5000 | L2: 5000 | M2: 5930
A3: Kinderg | B3: 510 | C3: 518 | D3: 518 | E3: 518 | F3: 518 | G3: 510 | H3: 510 | I3: 510 | J3: 510 | K3: 510 | L3: 510 | M3: 518
A4: Bina | B4: 1350 | C4: 1350 | D4: 1350 | E4: 1350 | F4: 1350 | G4: 1280 | H4: 1280 | I4: 1280 | J4: 1280 | K4: 1280 | L4: 1280 | M4: 1350
A5: Mieteinnahmen | D5: 650 | E5: 650 | F5: 650 | M5: 650
A6: Zinseinnahmen | B6: 70 | C6: 70 | D6: 70 | E6: 70 | F6: 70 | M6: 70
A7: Summe IC | B7: =SUM(B2:B6) -> 7580 | C7: =SUM(C2:C6) -> 7868 | D7: =SUM(D2:D6) -> 8518 | E7: =SUM(E2:E6) -> 8518 | F7: =SUM(F2:F6) -> 7818 | G7: =SUM(G2:G4) -> 7390 | H7: =SUM(H2:H4) -> 7390 | I7: =SUM(I2:I4) -> 7390 | J7: =SUM(J2:J4) -> 6790 | K7: =SUM(K2:K4) -> 6790 | L7: =SUM(L2:L4) -> 6790 | M7: =SUM(M2:M6) -> 8518
A8: BU | B8: vom Brutto | C8: 105 | D8: 109 | E8: 109 | F8: 109 | G8: 0 | M8: 109
A9: Esse Ar | B9: bereits abgezogen | C9: bereits abgezogen | D9: bereits abgezogen | E9: bereits abgezogen | F9: bereits abgezogen | G9: 100 | H9: 100 | I9: 100 | J9: 100 | K9: 100 | L9: 100 | M9: bereits abgezogen
A10: heiz | B10: 130 | C10: 145 | D10: 145 | E10: 145 | F10: 145 | G10: 100 | H10: 100 | I10: 100 | J10: 100 | K10: 100 | L10: 100 | M10: 145
A11: miete/ rate | B11: 1225 | C11: 1225 | D11: 1225 | E11: 1225 | F11: 1225 | G11: 3000 | H11: 3000 | I11: 3000 | J11: 3000 | K11: 3000 | L11: 3000 | M11: 1225
A12: NK Mietwohnung | D12: 70 | E12: 70 | F12: 70 | M12: 70
A13: kredit wohnung | C13: 623 | D13: 1350 | E13: 1350 | F13: 1350 | M13: 1350
A14: DAZN | B14: 35 | C14: 35 | D14: 35 | E14: 35 | F14: 35 | G14: 25 | H14: 25 | J14: 25 | K14: 25 | M14: 35
A15: mietfahrzeug | B15: 693 | C15: 488 | D15: 488 | E15: 488 | F15: 488 | G15: 550 | H15: 400 | I15: 350 | J15: 550 | K15: 400 | L15: 350 | M15: 488
A16: strom | B16: 130 | C16: 65 | D16: 65 | E16: 65 | F16: 65 | G16: 115 | H16: 115 | I16: 115 | J16: 115 | K16: 115 | L16: 115 | M16: 100 | Q16: 750
A17: sky | B17: 71 | C17: 71 | D17: 71 | E17: 71 | F17: 71 | G17: 62 | H17: 62 | J17: 62 | K17: 62 | M17: 71 | Q17: 250
A18: intern | B18: 43 | C18: 43 | D18: 43 | E18: 43 | F18: 43 | G18: 43 | H18: 43 | I18: 43 | J18: 43 | K18: 43 | L18: 43 | M18: 43 | Q18: 80
A19: handy | B19: 50 | C19: 50 | D19: 40 | E19: 40 | F19: 40 | G19: 40 | H19: 40 | I19: 40 | J19: 40 | K19: 40 | L19: 40 | M19: 40 | P19: =Q16-Q17-Q18 -> 420
A20: Spotify | B20: 11 | C20: 13 | D20: 13 | E20: 13 | F20: 13 | G20: 11 | H20: 11 | I20: 11 | J20: 11 | K20: 11 | L20: 11 | M20: 13 | Q20: 300
A21: Rundfunk | B21: 18 | C21: 18 | D21: 18 | E21: 18 | F21: 18 | M21: 18 | P21: =P19-Q20 -> 120
A22: Bargeld | B22: 450 | C22: 400 | D22: 400 | E22: 400 | F22: 400 | G22: 450 | H22: 450 | I22: 450 | J22: 450 | K22: 450 | L22: 450 | M22: 400
A23: Shopping | B23: 650 | C23: 700 | D23: 700 | E23: 700 | F23: 500 | G23: 850 | H23: 650 | I23: 450 | J23: 850 | K23: 650 | L23: 450 | M23: 700
A24: Benzin + Wartung | B24: 300 | C24: 300 | D24: 300 | E24: 300 | F24: 300 | G24: 300 | H24: 300 | I24: 300 | J24: 300 | K24: 300 | L24: 300 | M24: 300
A25: Lebensmittel | B25: 800 | C25: 800 | D25: 800 | E25: 800 | F25: 800 | G25: 850 | H25: 850 | I25: 800 | J25: 850 | K25: 850 | L25: 800 | M25: 800
A26: Investition Aktien | B26: 1100 | C26: 710 | D26: 710 | E26: 710 | F26: 610 | M26: 710
A27: Altersvorsorgedepot | M27: 300
A28: Reiten | C28: 90 | D28: 90 | E28: 90 | F28: 90 | M28: 90
A29: Sonstiges | B29: 500 | C29: 400 | D29: 400 | E29: 400 | F29: 350 | M29: 400
A30: Ausgaben | B30: =SUM(B8:B29) -> 6206 | C30: =SUM(C8:C29) -> 6281 | D30: =SUM(D8:D29) -> 7072 | E30: =SUM(E8:E29) -> 7072 | F30: =SUM(F8:F29) -> 6722 | G30: =SUM(G8:G25) -> 6496 | H30: =SUM(H8:H25) -> 6146 | I30: =SUM(I8:I25) -> 5759 | J30: =SUM(J8:J25) -> 6496 | K30: =SUM(K8:K25) -> 6146 | L30: =SUM(L8:L25) -> 5759 | M30: =SUM(M8:M29) -> 7407
A31: Übertrag | B31: =B7-B30 -> 1374 | C31: =C7-C30 -> 1587 | D31: =D7-D30 -> 1446 | E31: =E7-E30 -> 1446 | F31: =F7-F30 -> 1096 | G31: =G7-G30 -> 894 | H31: =H7-H30 -> 1244 | I31: =I7-I30 -> 1631 | ... M31: =M7-M30 -> 1111
A32: Sonderzahlung Umlage ohne Gewinnbeteiligung (GWB) | B32: 1000 | C32: =$B$67 -> 825 | D32: =$B$67 -> 825 | E32: =$C$67 -> 504.16667 | F32: =$C$67 -> 504.16667 | G32: 1000 | H32: 1000 | I32: 1000 | J32: 1000 | K32: 1000 | L32: 1000 | M32: =$C$67 -> 504.16667
A33: Versicherung | B33: 225 | C33: 175 | D33: 175 | E33: 175 | F33: 175 | G33: 270 | H33: 270 | I33: 270 | J33: 270 | K33: 270 | L33: 270 | M33: 175
A34: Überschuss | B34: =B31+B32-B33 -> 2149 | C34: =C31+C32-C33 -> 2237 | D34: =D31+D32-D33 -> 2096 | E34: =E31+E32-E33 -> 1775.1667 | F34: =F31+F32-F33 -> 1425.1667 | G34: =G31+G32 -> 1894 | H34: =H31+H32 -> 2244 | I34: =I31+I32 -> 2631 | J34: =J31+J32 -> 1294 | K34: =K31+K32 -> 1644 | L34: =L31+L32 -> 2031 | M34: =M31+M32-M33 -> 1440.1667
A35: Überschuss/ Jahr ohne GWB | B35: =B34*12 -> 25788 | C35: =C34*12 -> 26844 | D35: =D34*12 -> 25152 | E35: =E34*12 -> 21302 | F35: =F34*12 -> 17102 | M35: =M34*12 -> 17282
A36: Überschuss/ Jahr ink. GWB | B36: =B35+$B$61 -> 30788 | C36: =C35+$B$61 -> 31844 | D36: =D35+$B$61 -> 30152 | E36: =E35+$B$61 -> 26302 | F36: =F35+$B$61 -> 22102 | M36: =M35+$B$61 -> 22282
A39: Summe Income/ Jahr | B39: =B7*12 -> 90960 | C39: =C7*12 -> 94416 | D39: =D7*12 -> 102216 | E39: =E7*12 -> 102216 | F39: =F7*12 -> 93816 | G39: =G7*12 -> 88680 | H39: =H7*12 -> 88680 | I39: =I7*12 -> 88680 | ... M39: =M7*12 -> 102216
A40: Summe Ausgabe/ Jahr | B40: =B30*12+B33*12 -> 77172 | C40: =C30*12+C33*12 -> 77472 | D40: =D30*12+D33*12 -> 86964 | E40: =E30*12+E33*12 -> 86964 | F40: =F30*12+F33*12 -> 82764 | G40: =G30*12 -> 77952 | H40: =H30*12 -> 73752 | I40: =I30*12 -> 69108 | J40: =J30*12 -> 77952 | K40: =K30*12 -> 73752 | L40: =L30*12 -> 69108 | M40: =M30*12+M33*12 -> 90984 | Q40: =E40-(E26*12+E5*12) -> 70644
A41: Übertrag/ Jahr | B41: =B39-B40 -> 13788 | C41: =C39-C40 -> 16944 | D41: =D39-D40 -> 15252 | E41: =E39-E40 -> 15252 | F41: =F39-F40 -> 11052 | G41: =G39-G40 -> 10728 | H41: =H39-H40 -> 14928 | I41: =I39-I40 -> 19572 | ... M41: =M39-M40 -> 11232
A42: Sonderzahlung/Jahr | B42: 10000 | C42: 10000 | D42: 10000 | E42: =$C$66 -> 6050 | F42: =$C$66 -> 6050 | G42: =F42 -> 6050 | H42: =G42 -> 6050 | I42: =H42 -> 6050 | J42: =I42 -> 6050 | K42: =J42 -> 6050 | L42: =K42 -> 6050 | M42: =$C$66 -> 6050
A43: Steuererstattung | B43: 1500 | C43: 2000 | D43: 3000 | E43: 3000 | F43: 3000 | M43: 3000
A44: BMW Dividende | B44: 800 | C44: 800 | D44: 800 | E44: 400 | F44: 400 | M44: 400 | T44: Sparen | U44: Einnahmen
A45: Übertrag+SZ/Jahr | B45: =SUM(B41:B44) -> 26088 | C45: =SUM(C41:C44) -> 29744 | D45: =SUM(D41:D44) -> 29052 | E45: =SUM(E41:E44) -> 24702 | F45: =SUM(F41:F44) -> 20502 | G45: =SUM(G41:G42) -> 16778 | H45: =SUM(H41:H42) -> 20978 | I45: =SUM(I41:I42) -> 25622 | J45: =SUM(J41:J42) -> 9578 | K45: =SUM(K41:K42) -> 13778 | L45: =SUM(L41:L42) -> 18422 | M45: =SUM(M41:M44) -> 20682 | S45: Wohnung | T45: =750*12 -> 9000 | U45: 102216
A46: Aktieninvest/ Jahr | B46: =B26*12 -> 13200 | C46: =C26*12 -> 8520 | D46: =D26*12 -> 8520 | E46: =E26*12 -> 8520 | F46: =F26*12 -> 7320 | G46: 3500 | H46: 3000 | I46: 2000 | J46: 3500 | K46: 3000 | L46: 2000 | M46: =M26*12 -> 8520
A47: Urlaub | B47: 7000 | C47: 7000 | D47: 7000 | E47: 7000 | F47: 5500 | M47: 7000 | S47: Wohnung Sondertilgung | T47: 10000 | U47: 10000
A48: Einrichtung | B48: 2000 | C48: 2000 | D48: 2000 | E48: 2000 | F48: 1500 | M48: 2000 | S48: Aktien | T48: =710*12 -> 8520 | U48: 5000
A49: Übertrag+SZ/Jahr-Aktien&Urlaub | B49: =B45-B47-B48 -> 17088 | C49: =C45-C47-C48 -> 20744 | D49: =D45-D47-D48 -> 20052 | E49: =E45-E47-E48 -> 15702 | F49: =F45-F47-F48 -> 13502 | M49: =M45-M47-M48 -> 11682 | S49: Überschuss | T49: 14000 | U49: 2500
A50: Sonderzahlung Wohnung | C50: 10000 | D50: 10000 | E50: 8000 | F50: 8000 | M50: 8000 | S50: Summe | T50: =SUM(T45:T49) -> 41520 | U50: =SUM(U45:U49) -> 119716
A51: ÜbertragFINAL/Jahr (Tagesgeld) | B51: =B49-B50 -> 17088 | C51: =C49-C50 -> 10744 | D51: =D49-D50 -> 10052 | E51: =E49-E50 -> 7702 | F51: =F49-F50 -> 5502 | G51: =G45-G50-G46 -> 13278 | H51: =H45-H50-H46 -> 17978 | I51: =I45-I50-I46 -> 23622 | J51: =J45-J50-J46 -> 6078 | K51: =K45-K50-K46 -> 10778 | L51: =L45-L50-L46 -> 16422 | M51: =M49-M50 -> 3682 | U51: =T50/U50 -> 0.34682081
A52: ÜbertragFINAL/Monat (Tagesgeld) | B52: =B51/12 -> 1424 | C52: =C51/12 -> 895.33333 | D52: =D51/12 -> 837.66667 | E52: =E51/12 -> 641.83333 | F52: =F51/12 -> 458.5 | M52: =M51/12 -> 306.83333
A53: optional: inkl. GWB (Tagesgeld) | B53: =B51+B61 -> 22088 | C53: =C51+B61 -> 15744 | D53: =D51+B61 -> 15052 | E53: =E51+C61 -> 8202 | F53: =F51+C61 -> 6002 | G53: =G51+4000 -> 17278 | H53: =H51+4000 -> 21978 | I53: =I51+4000 -> 27622 | J53: =J51+4000 -> 10078 | K53: =K51+4000 -> 14778 | L53: =L51+4000 -> 20422 | M53: =M51+B61 -> 8682
A55: Gesamtsumme Einnahmen [netto] | B55: =SUM(B39,B42,B43,B44,B61) -> 108260 | C55: =SUM(C39,C42,C43,C44,B61) -> 112216 | D55: =SUM(D39,D42,D43,D44,B61) -> 121016 | E55: =SUM(E39,E42,E43,E44,C61) -> 112166 | F55: =SUM(F39,F42,F43,F44,C61) -> 103766 | M55: =SUM(M39,M42,M43,M44,B61) -> 116666
A56: Gesamtsumme Ausgaben | B56: =SUM(B40,B47,B48)-B26*12 -> 72972 | C56: =SUM(C40,C47,C48)-C26*12 -> 77952 | D56: =SUM(D40,D47,D48)-D26*12 -> 87444 | E56: =SUM(E40,E47,E48)-E26*12 -> 87444 | F56: =SUM(F40,F47,F48)-F26*12 -> 82444 | M56: =SUM(M40,M47,M48)-M26*12 -> 91464
A57: Gesamtsumme Sparen | B57: =SUM(B26*12+B53) -> 35288 | C57: =SUM(C26*12+C53+C50) -> 34264 | D57: =SUM(D26*12+D53+D50+7000) -> 40572 | E57: =SUM(E26*12+E53+E50+7000) -> 31722 | F57: =SUM(F26*12+F53+F50+7000) -> 28322 | M57: =SUM(M26*12+M53+M50+7000+M27*12) -> 35802
A58: Sparquote | B58: =B57/B55 -> 0.32595603 | C58: =C57/C55 -> 0.3053397 | D58: =D57/D55 -> 0.33526145 | E58: =E57/E55 -> 0.28281297 | F58: =F57/F55 -> 0.27294104 | M58: =M57/M55 -> 0.30687604
A60: Aktien
A61: GewinnB | B61: 5000 | C61: 500
A62: Urlaub | B62: 4000 | C62: 4100
A63: Weihnachtsgeld | B63: 4250 | C63: 300
A64: T-Zug | B64: 650 | C64: 650
A65: T-Geld | B65: 1000 | C65: 1000
A66: Summe | B66: =SUM(B62:B65) -> 9900 | C66: =SUM(C62:C65) -> 6050
A67: Umlage var. | B67: =B66/12 -> 825 | C67: =C66/12 -> 504.16667
B71: aktuell | D71: aktuell | G71: mit Haus | I71: mit Haus und Maßnahme
A73: wohnen | B73: 1580 | D73: 3000 | G73: 3580 | I73: 3580
A74: Lifestyle | B74: 1000 | D74: 1000 | G74: 1000 | I74: 700
A75: Freizeit | B75: 1000 | D75: 1000 | G75: 1000 | I75: 650
A76: Essen | B76: 950 | D76: 950 | G76: 950 | I76: 950
A77: Auto | B77: 850 | D77: 850 | G77: 800 | I77: 750
A78: Bargeld | B78: 500 | D78: 500 | G78: 500 | I78: 500
A79: Versicherung | B79: 270 | D79: 270 | G79: 270 | I79: 270
A80: Drogerie | B80: 150 | D80: 150 | G80: 150 | I80: 150
A81: Gesundheit | B81: 100 | D81: 100 | G81: 100 | I81: 100
A82: Haustier | B82: 30 | D82: 30 | G82: 30 | I82: 30
A83: Ausgaben | B83: =SUM(B73:B82) -> 6430 | D83: =SUM(D73:D82) -> 7850 | G83: =SUM(G73:G82) -> 8380 | I83: =SUM(I73:I82) -> 7680
A85: Lohn/Gehalt | B85: 7875 | D85: 7875 | G85: 7875 | I85: 7875
A86: Kindergeld | B86: 510 | D86: 1200 | G86: 510 | I86: 510
A87: Einnahmen | B87: =SUM(B85:B86) -> 8385 | D87: =SUM(D85:D86) -> 9075 | G87: =SUM(G85:G86) -> 8385 | I87: =SUM(I85:I86) -> 8385
A89: Überschuss | B89: =B87-B83 -> 1955 | D89: =D87-D83 -> 1225 | G89: =G87-G83 -> 5 | I89: =I87-I83 -> 705
A90: Überschuss Jahr | B90: =B89*12 -> 23460 | D90: =D89*12 -> 14700 | G90: =G89*12 -> 60 | I90: =I89*12 -> 8460
B95: aktuell | G95: mit Haus | I95: mit Haus und Maßnahme
A97: Einnahmen 2024 | B97: 109000 | G97: 105000 | I97: 105000
A98: Ausgaben 2024 | B98: 80000 | G98: 102000 | I98: 95000
A99: Überschuss Jahr | B99: =B97-B98 -> 29000 | G99: =G97-G98 -> 3000 | I99: =I97-I98 -> 10000

Sheet Haushalt (Cash)
A1: Kontostand | B1: Datum | C1: Betrag | E1: Ausgaben | F1: Datum | G1: Betrag | I1: Einnahmen | J1: Datum | K1: Betrag | P1: 2026 | Q1: Prognose
A2: IST | B2: 46133 | C2: 46419 | E2: 5.Rate Wohnung | F2: 46157 | G2: 6960 | I2: 2026 Einnahmen | J2: Prognose | K2: =K24 -> 31758 | O2: Jan | P2: 65
E3: Sonderwunsch Rollos + Spots | F3: Prognose | G3: 2000 | I3: 2026 Rückerstattung Wohnung | J3: Prognose | K3: 5332 | O3: Feb | P3: 1818
E4: Sonderwunsch Fließen | F4: Prognose | G4: 1141 | O4: Mrz | P4: 1489
E5: Sondertilgung 2026 | F5: Prognose | G5: 10000 | O5: Apr | P5: 1200 | Q5: =1200-R5 -> -870 | R5: 2070
A6: Kontostand | B6: Datum | C6: Betrag | E6: Balkonkraftwerk | F6: 46136 | G6: 2070 | O6: Mai | P6: 1830 | Q6: =2014-S6+R6-T6-U6 -> -8715 | R6: 820 | S6: 3789 | T6: 800 | U6: 6960
A7: PROGNOSE | B7: 46387 | C7: =C2-G12+K12 -> 47934 | E7: Urlaub Schreinerhof | F7: 46173 | G7: 3789 | O7: Jun | P7: 1850 | Q7: =1500+S7+R7-T7 -> 3500 | R7: 2000 | S7: 4000 | T7: 4000
A8: PROGNOSE | B8: 46752 | C8: =C7+$G$38 -> 59884 | E8: Urlaub Österreich | F8: Prognose | G8: 2400 | O8: Jul | P8: 1500 | Q8: =1500+S8-R8-T8 -> 1300 | R8: 2400 | S8: 5000 | T8: 2800
A9: PROGNOSE | B9: 47118 | C9: =C8+$G$38 -> 71834 | E9: Vorhalt Möbelkauf | F9: 46173 | G9: 3575 | O9: Aug | P9: 1500 | Q9: =1500-S9+R9-T9+U9 -> -7018 | R9: 1000 | S9: 10000 | T9: 2840 | U9: 3322
A10: PROGNOSE | B10: 47483 | C10: =C9+$G$38 -> 83784 | E10: Rate Küche | F10: 46157 | G10: 800 | O10: Sep | P10: 1500 | Q10: =1500-R10 -> 1500
A11: PROGNOSE | B11: 47848 | C11: =C10+$G$38 -> 95734 | E11: Letzte Rate Wohnung | F11: Prognose | G11: 2840 | O11: Oktober | P11: 1500 | Q11: 1500
A12: PROGNOSE | B12: 48213 | C12: =C11+$G$38 -> 107684 | E12: Summe | F12: Prognose | G12: =SUM(G2:G11) -> 35575 | I12: Summe | J12: Prognose | K12: =SUM(K2:K11) -> 37090 | O12: November | P12: 1500 | Q12: =1500+S12+R12 -> 6600 | R12: 4500 | S12: 600
A13: PROGNOSE | B13: 48579 | C13: =C12+$G$38 -> 119634 | E13: Summe (Ausstehend) | G13: =SUMIF(F2:F11,"Prognose",G2:G11) -> 18381 | O13: Dezember | P13: 1500 | Q13: 1500
A14: PROGNOSE | B14: 48944 | C14: =C13+$G$38 -> 131584 | P14: =AVERAGE(P2:P13) -> 1437.6667 | Q14: =AVERAGE(Q2:Q13) -> -78.111111
A15: PROGNOSE | B15: 49309 | C15: =C14+$G$38 -> 143534 | E15: Überschuss/ Unterdeckung 2026 | G15: =K12-G12 -> 1515
A16: PROGNOSE | B16: 49674 | C16: =C15+$G$38 -> 155484 | I16: 9 Monate Überschuss | J16: 46161 | K16: =SUM(P5:P13) -> 13880
A17: PROGNOSE | B17: 50040 | C17: =C16+$G$38 -> 167434 | I17: Weihnachtsgeld Bina | J17: Prognose | K17: 600
A18: PROGNOSE | B18: 50405 | C18: =C17+$G$38 -> 179384 | I18: Steuer | J18: Prognose | K18: 2000
A19: PROGNOSE | B19: 50770 | C19: =C18+$G$38 -> 191334 | I19: Urlaubsgeld | J19: 46203 | K19: 4100
A20: PROGNOSE | B20: 51135 | C20: =C19+$G$38 -> 203284 | I20: Weihnachtsgeld | J20: Prognose | K20: 4150
I21: GB | J21: Prognose | K21: 5200
I22: Dividende | J22: 46161 | K22: 828
I23: Transformationsgeld | J23: Prognose | K23: 1000
I24: Summe | K24: =SUM(K16:K23) -> 31758
I25: Summe (Ausstehend) | K25: =SUMIF(J17:J23,"Prognose",K17:K23)+SUM(P8:P13) -> 21950
E27: Ausgaben | F27: Datum | G27: Betrag | I27: generische Einnahmen | J27: Datum | K27: Betrag
E28: Sondertilgung | F28: Prognose | G28: 10000 | I28: Summe Monatsüberschüse | J28: Prognose | K28: =K51 -> 33450
E30: Urlaub | F30: Prognose | G30: 4500
E31: Urlaub | F31: Prognose | G31: 2500
E32: Vorhalt Möbelkauf | F32: Prognose | G32: 1500
E33: Pauschale | F33: Prognose | G33: 3000
E35: Summe | F35: Prognose | G35: =SUM(G28:G34) -> 21500
D38: Überschuss/ Unterdeckung Generisch (normales Jahr) | G38: =K38-G35 -> 11950 | I38: Summe | J38: Prognose | K38: =SUM(K28:K37) -> 33450
D39: Überschuss/ Unterdeckung Generisch (schlechtes Jahr) | G39: =N51-G35 -> 3650
D40: Überschuss/ Unterdeckung Generisch (gutes Jahr) | G40: =Q51-G35 -> 16150
I42: Weihnachtsgeld Bina | K42: 600 | L42: Weihnachtsgeld Bina | N42: 600 | O42: Weihnachtsgeld Bina | Q42: 600
I43: Überschuss/ Monat | J43: 1250 | K43: =J43*12 -> 15000 | L43: Überschuss/ Monat | M43: 1000 | N43: =M43*12 -> 12000 | O43: Überschuss/ Monat | P43: 1400 | Q43: =P43*12 -> 16800
I44: Steuer | K44: 3500 | L44: Steuer | N44: 2800 | O44: Steuer | Q44: 4000
I45: Urlaubsgeld | K45: 4100 | L45: Urlaubsgeld | N45: 4000 | O45: Urlaubsgeld | Q45: 4000
I46: Weihnachtsgeld | K46: 4680 | L46: Weihnachtsgeld | N46: 3000 | O46: Weihnachtsgeld | Q46: 4680
I47: GB | K47: 3000 | L47: GB | N47: 500 | O47: GB | Q47: 5000
I48: Dividende | K48: 820 | L48: Dividende | N48: 500 | O48: Dividende | Q48: 820
I49: T-Zug Teil B | K49: 750 | L49: T-Zug Teil B | N49: 750 | O49: T-Zug Teil B | Q49: 750
I50: Transformationsgeld | K50: 1000 | L50: Transformationsgeld | N50: 1000 | O50: Transformationsgeld | Q50: 1000
I51: Summe (normales Jahr) | K51: =SUM(K42:K50) -> 33450 | L51: Summe (schlechtes Jahr) | N51: =SUM(N42:N50) -> 25150 | O51: Summe (gutes Jahr) | Q51: =SUM(Q42:Q50) -> 37650

Sheet Finanzierung&Mietkalkulation
A1: Kalkulation Wohnungskauf | G1: EK | I1: Kredit
F2: Startsumme | G2: 92000 | H2: Kredit | I2: 288000 | N2: Kaufpreis gesamt | O2: 360000
F3: Notar | G3: -2834.8 | H3: 1. Rate | I3: -200000 | N3: geleistete Zahlungen | O3: =SUM(I3:I5,G7:G9) -> -299160
F4: Notar Grundschuld | G4: -1213.9 | H4: 2. Rate | I4: -15000 | N4: ausstehend | O4: =O2+O3 -> 60840 | Q4: ausstehend aus EK | R4: =SUM(G10:G12) -> -5981.36
A5: Kaufpreis | B5: 322000 | F5: Grundbuch | G5: -1012.5 | H5: 5. Rate | I5: -15000
A6: Stellplätze | B6: 38000 | F6: Grunderwerbssteuer | G6: -12600
A7: Nebenkosten 10% | B7: 19800 | F7: 1. Rate | G7: -58840 | N7: Rate A | O7: =O$2*P7 -> 90000 | P7: 0.25
A8: Kosten Gesamt | B8: =SUM(B5:B7) -> 379800 | F8: 2. Rate | G8: -3360 | N8: Rate B | O8: =O$2*P8 -> 120960 | P8: 0.336
F9: 5. Rate | G9: -6960 | N9: Rate C | O9: =O$2*P9 -> 47880 | P9: 0.133
A10: EK | B10: 92000 | F10: Sonderwünsche Fließen | G10: -1141.36 | N10: Rate D | O10: =O$2*P10 -> 18360 | P10: 0.051
A11: Kredit | B11: 288000 | F11: Sonderwünsche Insekt | G11: -2000 | N11: Rate E | O11: =O$2*P11 -> 30240 | P11: 0.084
F12: EK letzte Rate | G12: -2840 | N12: Rate F | O12: =O$2*P12 -> 21960 | P12: 0.061
G13: =G2+SUM(G3:G12) -> -802.56 | I13: =I2+SUM(I3:I11) -> 58000 | N13: Rate G | O13: =O$2*P13 -> 12600 | P13: 0.035
N14: Rate A-2 | O14: =O$2*P14 -> 18000 | P14: 0.05
F15: verfügbares Tagesgeld | G15: 46419
F16: nach Abzug | G16: =G15-G13 -> 47221.56
F17: inkl. Puffer | G17: =G13-R4+G16 -> 52400.36
E26: Zinskosten vor Tilgung | G26: 215000 | H26: 0.0348 | I26: =G26*H26 -> 7482
I27: =I26/12 -> 623.5
I28: =I27*7 -> 4364.5
A32: Mietkalkulation | B32: 79.88 | C32: m²
C33: 0,66% Regel | E33: 0,66% Regel | G33: 0,66% Regel | I33: 0,66% Regel | K33: 0,66% Regel | M33: 0,66% Regel | O33: 0,66% Regel
A34: €/ m² | B34: 10 | C34: =B34*0.66 -> 6.6 | D34: 11 | E34: =D34*0.66 -> 7.26 | F34: 11.5 | G34: =F34*0.66 -> 7.59 | H34: 12.23 | I34: =H34*0.66 -> 8.0718 | J34: 12.91 | K34: =J34*0.66 -> 8.5206 | L34: 13 | M34: =L34*0.66 -> 8.58 | N34: 14 | O34: =N34*0.66 -> 9.24
A35: Kalt | B35: =B34*$B32 -> 798.8 | C35: =B35*0.66 -> 527.208 | D35: =D34*$B32 -> 878.68 | E35: =D35*0.66 -> 579.9288 | F35: =F34*$B32 -> 918.62 | G35: =F35*0.66 -> 606.2892 | H35: =H34*$B32 -> 976.9324 | I35: =H35*0.66 -> 644.77538 | J35: =J34*$B32 -> 1031.2508 | K35: =J35*0.66 -> 680.62553 | L35: =L34*$B32 -> 1038.44 | M35: =L35*0.66 -> 685.3704 | N35: =N34*$B32 -> 1118.32 | O35: =N35*0.66 -> 738.0912
A36: Stellplatz | B36: 60 | C36: =B36*0.66 -> 39.6 | D36: 60 | E36: =D36*0.66 -> 39.6 | F36: 60 | G36: =F36*0.66 -> 39.6 | H36: 60 | I36: =H36*0.66 -> 39.6 | K36: =J36*0.66 -> 0 | L36: 60 | M36: =L36*0.66 -> 39.6 | N36: 60 | O36: =N36*0.66 -> 39.6
A37: Kaltmiete | B37: =SUM(B35:B36) -> 858.8 | C37: =SUM(C35:C36) -> 566.808 | D37: =SUM(D35:D36) -> 938.68 | E37: =SUM(E35:E36) -> 619.5288 | F37: =SUM(F35:F36) -> 978.62 | G37: =SUM(G35:G36) -> 645.8892 | H37: =SUM(H35:H36) -> 1036.9324 | I37: =SUM(I35:I36) -> 684.37538 | ... O37: =SUM(O35:O36) -> 777.6912
A38: 700 Kalt | C38: =700/B37 -> 0.81509082 | E38: =700/D37 -> 0.74572804 | G38: =700/F37 -> 0.71529296 | I38: =700/H37 -> 0.67506811 | K38: =700/J37 -> 0.67878735 | M38: =700/L37 -> 0.6372674 | O38: =700/N37 -> 0.59406613
A39: 750 Kalt | C39: =750/B37 -> 0.8733116 | E39: =750/D37 -> 0.79899433 | G39: =750/F37 -> 0.76638532 | I39: =750/H37 -> 0.72328727 | K39: =750/J37 -> 0.72727216 | M39: =750/L37 -> 0.6827865 | O39: =750/N37 -> 0.63649942
A40: NK | B40: 160 | C40: 2,30 €/m² | D40: 160 | E40: 2,30 €/m² | F40: 160 | G40: 2,30 €/m² | H40: 160 | I40: 2,30 €/m² | J40: 160 | K40: 2,30 €/m² | L40: 160 | M40: 2,30 €/m² | N40: 160 | O40: 2,30 €/m²
A41: Warmmiete | B41: =SUM(B37:B40) -> 1018.8 | C41: =B41*0.66 -> 672.408 | D41: =SUM(D37:D40) -> 1098.68 | E41: =D41*0.66 -> 725.1288 | F41: =SUM(F37:F40) -> 1138.62 | G41: =F41*0.66 -> 751.4892 | H41: =SUM(H37:H40) -> 1196.9324 | I41: =H41*0.66 -> 789.97538 | J41: =SUM(J37:J40) -> 1191.2508 | K41: =J41*0.66 -> 786.22553 | L41: =SUM(L37:L40) -> 1258.44 | M41: =L41*0.66 -> 830.5704 | N41: =SUM(N37:N40) -> 1338.32 | O41: =N41*0.66 -> 883.2912
A42: 0,66% Regel | B42: =B41*0.66 -> 672.408 | C42: =860/B41 -> 0.84413035 | D42: =D41*0.66 -> 725.1288 | E42: =860/D41 -> 0.78275749 | F42: =F41*0.66 -> 751.4892 | G42: =860/F41 -> 0.75530028 | H42: =H41*0.66 -> 789.97538 | I42: =860/H41 -> 0.7185034 | J42: =J41*0.66 -> 786.22553 | K42: =860/J41 -> 0.72193026 | L42: =L41*0.66 -> 830.5704 | M42: =860/L41 -> 0.68338578 | N42: =N41*0.66 -> 883.2912 | O42: =860/N41 -> 0.64259669
A44: Einnahmen Szenario 1 | B44: 810 | D44: 810 | F44: 810 | H44: 810 | J44: 810 | L44: 810 | N44: 810
A45: Differenz | B45: =B42-B44 -> -137.592 | D45: =D42-D44 -> -84.8712 | F45: =F42-F44 -> -58.5108 | H45: =H42-H44 -> -20.024616 | J45: =J42-J44 -> -23.774472 | L45: =L42-L44 -> 20.5704 | N45: =N42-N44 -> 73.2912
A47: Einnahmen Szenario 2 | B47: 900 | D47: 900 | F47: 900 | H47: 900 | J47: 900 | L47: 900 | N47: 900
A48: Differenz | B48: =B42-B47 -> -227.592 | D48: =D42-D47 -> -174.8712 | F48: =F42-F47 -> -148.5108 | H48: =H42-H47 -> -110.02462 | J48: =J42-J47 -> -113.77447 | L48: =L42-L47 -> -69.4296 | N48: =N42-N47 -> -16.7088
A50: Einnahmen Szenario 2 | B50: 950 | D50: 950 | F50: 950 | H50: 950 | J50: 950 | L50: 950 | N50: 950
A51: Differenz | B51: =B42-B50 -> -277.592 | D51: =D42-D50 -> -224.8712 | F51: =F42-F50 -> -198.5108 | H51: =H42-H50 -> -160.02462 | J51: =J42-J50 -> -163.77447 | L51: =L42-L50 -> -119.4296 | N51: =N42-N50 -> -66.7088
A53: Subvention Eltern/ Jahr | B53: =B35-650 -> 148.8 | C53: =B53*12 -> 1785.6 | D53: =D35-650 -> 228.68 | E53: =D53*12 -> 2744.16 | F53: =F35-650 -> 268.62 | G53: =F53*12 -> 3223.44 | H53: =H35-650 -> 326.9324 | I53: =H53*12 -> 3923.1888 | J53: =J35-650 -> 381.2508 | K53: =J53*12 -> 4575.0096 | L53: =L35-650 -> 388.44 | M53: =L53*12 -> 4661.28 | N53: =N35-650 -> 468.32 | O53: =N53*12 -> 5619.84
A54: Subvention Eltern/ 15 Jahre | C54: =C53*15 -> 26784 | E54: =E53*15 -> 41162.4 | G54: =G53*15 -> 48351.6 | I54: =I53*15 -> 58847.832 | K54: =K53*15 -> 68625.144 | M54: =M53*15 -> 69919.2 | O54: =O53*15 -> 84297.6
A56: Mietkalkulation | B56: 75 | C56: m² | E56: 79.88 | F56: m²
C57: 0,66% Regel | F57: 0,66% Regel
A58: €/ m² | B58: =B59/B56 -> 13.2 | C58: =B58*0.66 -> 8.712 | E58: 13.2 | F58: =E58*0.66 -> 8.712
A59: Kalt | B59: 990 | C59: =B59*0.66 -> 653.4 | E59: =E58*E56 -> 1054.416 | F59: =E59*0.66 -> 695.91456
A60: NK | B60: 160 | E60: 160
A61: Warmmiete | B61: =SUM(B58:B60) -> 1163.2 | C61: =B61*0.66 -> 767.712 | E61: =SUM(E58:E60) -> 1227.616 | F61: =E61*0.66 -> 810.22656

Sheet (SOLL) Prognosekurve
A1: Kalkulation Wohnungskauf | E1: IST
D2: Sparkonto | E2: 45300
D3: Abweichung Ziel in € | E3: =E2-E34 -> -2634
A4: Kaufpreis | B4: 322000 | D4: Abweichung Ziel in % | E4: =E3/E2 -> -0.058145695 | N4: Rate | O4: 1350 | P4: 1350
A5: Stellplätze (2 Stück) | B5: 38000 | D5: DEPOT | E5: 132319 | N5: NK | O5: 80 | P5: 80
A6: Nebenkosten 10% | B6: 19800 | D6: Abweichung Ziel in € | E6: =E5-E39 -> -6813.07 | N6: Entfall Zinsen | O6: 140 | P6: 140
A7: Kosten Gesamt | B7: =SUM(B4:B6) -> 379800 | D7: Abweichung Ziel in % | E7: =E6/E5 -> -0.051489733 | N7: Mehrbelastung | O7: =SUM(O4:O6) -> 1570 | P7: =SUM(P4:P6) -> 1570
D8: Wohnung | E8: 69160 | N8: Miete | O8: 650 | P8: 650
A9: EK | B9: 92000 | D9: Abweichung Ziel in € | E9: =E8-E42 -> -16273.83 | N9: Reduz. Aktie | O9: 300 | P9: 300
A10: Kredit | B10: =B7-B9 -> 287800 | D10: Abweichung Ziel in % | E10: =E9/E8 -> -0.23530697 | N10: Reduz. Auto | O10: 240 | P10: 240
A11: Kredit Bank | B11: 0.0348 | D11: AVD BMW | E11: 93933 | N11: BAV | O11: 70 | P11: 70
A12: Rate | B12: 1350 | D12: Abweichung Ziel in € | E12: =E11-E49 -> -4662 | N12: Lohnlus 2026 | O12: 150
A13: Mieteinnahmen ab 01.06.2026 | B13: 650 | D13: Abweichung Ziel in % | E13: =E12/E11 -> -0.04963112
A14: geschätzter Überschuss/ Jahr | B14: 32000 | D14: Summe Abweichung in € | E14: =SUM(E3,E6,E9,E12) -> -30382.9 | N14: Steuereffekt | O14: 75
A15: Aktienkauf jährlich (600 mtl.) | B15: =600*12 -> 7200 | D15: Summe Abweichung in % | E15: =E14/E53 -> -0.081873666 | M15: abs. Mehrbelastung mtl. | O15: =O7-SUM(O8:O14) -> 85 | P15: =P7-SUM(P8:P14) -> 310
A16: Jährlicher Überschuss nach Aktienkauf | B16: =B14-B15 -> 24800 | M16: abs. Mehrbelastung jährlich | O16: =O15*12 -> 1020 | P16: =P15*12 -> 3720
A17: Jährliche Sondertilgung | B17: 10000
A18: Überschuss | B18: =B16-B17 -> 14800 | C18: Risikoabschlag | D18: ='Haushalt (Cash)'!G38 -> 11950
A19: Rendite Depot | B19: 1.07
A20: Rendite BMW AV | B20: 1.05
A28: Sparkonto | B28: 116000
A29: Depot | B29: 104600
A31: Alter | E31: 37 | F31: 38 | G31: 39 | H31: 40 | I31: 41 | J31: 42 | K31: 43 | L31: 44 | M31: 45 | N31: 46 | O31: 47 | P31: 48 | Q31: 49 | R31: 50 | S31: 51 | T31: 52 | U31: 53 | V31: 54 | W31: 55 | X31: 56 | Y31: 57 | Z31: 58 | AA31: 59 | AB31: 60 | AC31: 61 | AD31: 62 | AE31: 63
E32: 1 | F32: 2 | G32: 3 | H32: 4 | I32: 5 | J32: 6 | K32: 7 | L32: 8 | M32: 9 | N32: 10 | O32: 11 | P32: 12 | Q32: 13 | R32: 14 | S32: 15 | T32: 16 | U32: 17 | V32: 18 | W32: 19 | X32: 20 | Y32: 21 | Z32: 22 | AA32: 23 | AB32: 24 | AC32: 25 | AD32: 26 | AE32: 27
B33: 2025 | C33: 2025 n.K. | D33: Ende 2025 | E33: Ende 2026 | F33: Ende 2027 | G33: Ende 2028 | H33: Ende 2029 | I33: Ende 2030 | J33: Ende 2031 | K33: Ende 2032 | L33: Ende 2033 | M33: Ende 2034 | N33: Ende 2035 | O33: Ende 2036 | P33: Ende 2037 | Q33: Ende 2038 | R33: Ende 2039 | S33: Ende 2040 | T33: Ende 2041 | U33: Ende 2042 | V33: Ende 2043 | W33: Ende 2044 | X33: Ende 2045 | Y33: Ende 2046 | Z33: Ende 2047 | AA33: Ende 2048 | AB33: Ende 2049 | AC33: Ende 2050 | AD33: Ende 2051 | AE33: Ende 2052
A34: Sparkonto | B34: =B28 -> 116000 | C34: =B34-B9 -> 24000 | D34: 30000 | E34: ='Haushalt (Cash)'!C7 -> 47934 | F34: =E34+$D18 -> 59884 | G34: =F34-F35+$D18 -> 61950 | H34: =G34-G35+$D18 -> 61950 | I34: =H34-H35+$D18 -> 61950 | J34: =I34-I35+$D18 -> 61950 | K34: =J34-J35+$D18 -> 61950 | L34: =K34-K35+$D18 -> 61950 | M34: =L34-L35+$D18 -> 61950 | N34: =M34-M35+$D18 -> 61950 | ... AE34: =AD34-AD35+$D18 -> 61950
A35: Überschuss Grenze 50K | F35: =F34-50000 -> 9884 | G35: =G34-50000 -> 11950 | H35: =H34-50000 -> 11950 | I35: =I34-50000 -> 11950 | J35: =J34-50000 -> 11950 | K35: =K34-50000 -> 11950 | L35: =L34-50000 -> 11950 | M35: =M34-50000 -> 11950 | ... AE35: =AE34-50000 -> 11950
A36: Tilgunsendeüberschuss | S36: =1350*9 -> 12150 | T36: =1350*12 -> 16200 | U36: =1350*12 -> 16200 | V36: =1350*12 -> 16200 | W36: =1350*12 -> 16200 | X36: =1350*12 -> 16200 | Y36: =1350*12 -> 16200 | Z36: =1350*12 -> 16200 | AA36: =1350*12 -> 16200 | ... AE36: =1350*12 -> 16200
A38: Depot ohne Rendite | B38: 104600 | D38: =D39/1.07 -> 115234.58 | E38: =D38+B15 -> 122434.58 | F38: =E38+B15 -> 129634.58 | G38: =F38+$B15+F35 -> 146718.58 | H38: =G38+$B15+G35 -> 165868.58 | I38: =H38+$B15+H35 -> 185018.58 | J38: =I38+$B15+I35 -> 204168.58 | K38: =J38+$B15+J35 -> 223318.58 | L38: =K38+$B15+K35 -> 242468.58 | M38: =L38+$B15+L35 -> 261618.58 | N38: =M38+$B15+M35 -> 280768.58 | ... S38: =R38+$B15+R35 -> 376518.58 | T38: =S38+$B15+S35+S36 -> 407818.58 | U38: =T38+$B15+T35+T36 -> 443168.58 | V38: =U38+$B15+U35+U36 -> 478518.58 | W38: =V38+$B15+V35+V36 -> 513868.58 | X38: =W38+$B15+W35+W36 -> 549218.58 | Y38: =X38+$B15+X35+X36 -> 584568.58 | Z38: =Y38+$B15+Y35+Y36 -> 619918.58 | AA38: =Z38+$B15+Z35+Z36 -> 655268.58 | ... AE38: =AD38+$B15+AD35+AD36 -> 796668.58
A39: Depot mit Rendite | D39: 123301 | E39: =(D39*$B19)+$B15 -> 139132.07 | F39: =(E39*$B19)+$B15 -> 156071.31 | G39: =(F39*$B19)+$B15+F35 -> 184080.31 | H39: =(G39*$B19)+$B15+G35 -> 216115.93 | I39: =(H39*$B19)+$B15+H35 -> 250394.04 | J39: =(I39*$B19)+$B15+I35 -> 287071.63 | K39: =(J39*$B19)+$B15+J35 -> 326316.64 | L39: =(K39*$B19)+$B15+K35 -> 368308.81 | M39: =(L39*$B19)+$B15+L35 -> 413240.42 | N39: =(M39*$B19)+$B15+M35 -> 461317.25 | ... S39: =(R39*$B19)+$B15+R35 -> 757147.96 | T39: =(S39*$B19)+$B15+S35+S36 -> 841448.32 | U39: =(T39*$B19)+$B15+T35+T36 -> 935699.7 | V39: =(U39*$B19)+$B15+U35+U36 -> 1036548.7 | W39: =(V39*$B19)+$B15+V35+V36 -> 1144457.1 | X39: =(W39*$B19)+$B15+W35+W36 -> 1259919.1 | Y39: =(X39*$B19)+$B15+X35+X36 -> 1383463.4 | Z39: =(Y39*$B19)+$B15+Y35+Y36 -> 1515655.9 | AA39: =(Z39*$B19)+$B15+Z35+Z36 -> 1657101.8 | ... AE39: =(AD39*$B19)+$B15+AD35+AD36 -> 2329074.4
A40: jährliche Depotmehrung | E40: =E39-D39 -> 15831.07 | F40: =F39-E39 -> 16939.245 | G40: =G39-F39 -> 28008.992 | H40: =H39-G39 -> 32035.621 | I40: =I39-H39 -> 34278.115 | J40: =J39-I39 -> 36677.583 | K40: =K39-J39 -> 39245.014 | L40: =L39-K39 -> 41992.165 | ... AE40: =AE39-AD39 -> 185406.73
A42: Wohnung Besitzanteil | D42: 62200 | E42: =SUM(TilgungsRechner!E13:E19,TilgungsRechner!G15)+D42+10000 -> 85433.83 | F42: =SUM(TilgungsRechner!E20:E32,TilgungsRechner!G27,TilgungsRechner!G28)+E42 -> 102307.57 | G42: =SUM(TilgungsRechner!E33:E45,TilgungsRechner!G41)+'(SOLL) Prognosekurve'!F42 -> 119777.98 | H42: =SUM(TilgungsRechner!E46:E58,TilgungsRechner!G54)+G42 -> 137866.15 | I42: =SUM(TilgungsRechner!E59:E71,TilgungsRechner!G67)+H42 -> 156593.93 | J42: =SUM(TilgungsRechner!E72:E84,TilgungsRechner!G80)+I42 -> 175983.93 | K42: =SUM(TilgungsRechner!E85:E97,TilgungsRechner!G93)+J42 -> 196059.56 | L42: =SUM(TilgungsRechner!E98:E110,TilgungsRechner!G106)+K42 -> 216845.09 | M42: =SUM(TilgungsRechner!E111:E123,TilgungsRechner!G119)+L42 -> 238365.59 | N42: =SUM(TilgungsRechner!E124:E136,TilgungsRechner!G132)+M42 -> 260647.07 | O42: =SUM(TilgungsRechner!E137:E149,TilgungsRechner!G145)+N42 -> 283716.44 | P42: =SUM(TilgungsRechner!E150:E162,TilgungsRechner!G157,TilgungsRechner!G158)+O42 -> 307601.55 | Q42: =SUM(TilgungsRechner!E163:E175,TilgungsRechner!G171)+P42 -> 332331.25 | R42: =SUM(TilgungsRechner!E176:E188,TilgungsRechner!G184)+Q42 -> 357935.4 | S42: =SUM(TilgungsRechner!E189:E190)+R42 -> 360628.16 | T42: 360000 | U42: =SUM(TilgungsRechner!G189:G190)+T42 -> 360000 | V42: =SUM(TilgungsRechner!H189:H190)+U42 -> 360000 | W42: 360000 | X42: 360000 | Y42: 360000 | Z42: 360000 | AA42: 360000 | AB42: 360000 | AC42: 360000 | AD42: 360000 | AE42: 360000
A43: Prozentualer Anteil | D43: =D42/360000 -> 0.17277778 | E43: =E42/360000 -> 0.23731619 | F43: =F42/360000 -> 0.28418771 | G43: =G42/360000 -> 0.33271662 | H43: =H42/360000 -> 0.38296153 | I43: =I42/360000 -> 0.43498313 | J43: =J42/360000 -> 0.48884424 | K43: =K42/360000 -> 0.5446099 | ... AE43: =AE42/360000 -> 1
A45: Wohnung Wert | B45: 360000 | C45: 1.02 | D45: 360000 | E45: =D45*$C45 -> 367200 | F45: =E45*$C45 -> 374544 | G45: =F45*$C45 -> 382034.88 | H45: =G45*$C45 -> 389675.58 | I45: =H45*$C45 -> 397469.09 | J45: =I45*$C45 -> 405418.47 | K45: =J45*$C45 -> 413526.84 | L45: =K45*$C45 -> 421797.38 | ... AE45: =AD45*$C45 -> 614479.13
A46: jährliche Wertsteigerung | E46: =E45-D45 -> 7200 | F46: =F45-E45 -> 7344 | G46: =G45-F45 -> 7490.88 | H46: =H45-G45 -> 7640.6976 | I46: =I45-H45 -> 7793.5116 | J46: =J45-I45 -> 7949.3818 | K46: =K45-J45 -> 8108.3694 | L46: =L45-K45 -> 8270.5368 | ... AE46: =AE45-AD45 -> 12048.61
A48: Altersvorsorge BMW ohne Rendite | D48: 85000 | E48: =91500+(200*7)+1000 -> 93900 | F48: =E48+(200*12)+800 -> 97100 | G48: =F48+(200*12)+800 -> 100300 | H48: =G48+(200*12)+800 -> 103500 | I48: =H48+(200*12)+800 -> 106700 | J48: =I48+(200*12)+800 -> 109900 | K48: =J48+(200*12)+800 -> 113100 | L48: =K48+(200*12)+800 -> 116300 | M48: =L48+(200*12)+800 -> 119500 | ... AE48: =AD48+(200*12)+800 -> 177100
A49: Altersvorsorge BMW mit Rendite | D49: 90000 | E49: =E48*$B$20 -> 98595 | F49: =E49*$B$20+(12*200)+1000 -> 106924.75 | G49: =F49*$B$20+(12*200)+1000 -> 115670.99 | H49: =G49*$B$20+(12*200)+1000 -> 124854.54 | I49: =H49*$B$20+(12*200)+1000 -> 134497.26 | J49: =I49*$B$20+(12*200)+1000 -> 144622.13 | K49: =J49*$B$20+(12*200)+1000 -> 155253.23 | L49: =K49*$B$20+(12*200)+1000 -> 166415.89 | M49: =L49*$B$20+(12*200)+1000 -> 178136.69 | ... AE49: =AD49*$B$20+(12*200)+1000 -> 524357.29
A51: Gesamtergebnis ohne BMW AV | D51: =D34+D39+D42 -> 215501 | E51: =E34+E39+E42 -> 272499.9 | F51: =F34+F39+F42 -> 318262.89 | G51: =G34+G39+G42 -> 365808.29 | H51: =H34+H39+H42 -> 415932.08 | I51: =I34+I39+I42 -> 468937.97 | J51: =J34+J39+J42 -> 525005.55 | K51: =K34+K39+K42 -> 584326.2 | ... AE51: =AE34+AE39+AE42 -> 2751024.4
A52: Gesamtergebnis mit Wertsteigerung Immo | E52: =E34+E39+E42+E46 -> 279699.9 | F52: =F34+F39+F42+F46 -> 325606.89 | G52: =G34+G39+G42+G46 -> 373299.17 | H52: =H34+H39+H42+H46 -> 423572.78 | I52: =I34+I39+I42+I46 -> 476731.48 | J52: =J34+J39+J42+J46 -> 532954.93 | K52: =K34+K39+K42+K46 -> 592434.57 | L52: =L34+L39+L42+L46 -> 655374.43 | ... AE52: =AE34+AE39+AE42+AE46 -> 2763073
A53: Gesamtergebnis | D53: =D34+D39+D42+D49 -> 305501 | E53: =E34+E39+E42+E49 -> 371094.9 | F53: =F34+F39+F42+F49 -> 425187.64 | G53: =G34+G39+G42+G49 -> 481479.28 | H53: =H34+H39+H42+H49 -> 540786.62 | I53: =I34+I39+I42+I49 -> 603435.23 | J53: =J34+J39+J42+J49 -> 669627.68 | K53: =K34+K39+K42+K49 -> 739579.44 | ... AE53: =AE34+AE39+AE42+AE49 -> 3275381.7
A54: Vermögenssteigerung in € | E54: =E53-D53 -> 65593.9 | F54: =F53-E53 -> 54092.74 | G54: =G53-F53 -> 56291.638 | H54: =H53-G53 -> 59307.341 | I54: =I53-H53 -> 62648.618 | J54: =J53-I53 -> 66192.445 | K54: =K53-J53 -> 69951.758 | L54: =L53-K53 -> 73940.348 | ... AE54: =AE53-AD53 -> 213614.22
A55: Vermögenssteigerung in % | E55: =E54/D53 -> 0.21470928 | F55: =F54/E53 -> 0.14576525 | G55: =G54/F53 -> 0.13239246 | H55: =H54/G53 -> 0.12317735 | I55: =I54/H53 -> 0.1158472 | J55: =J54/I53 -> 0.10969271 | K55: =K54/J53 -> 0.10446366 | L55: =L54/K53 -> 0.099976208 | ... AE55: =AE54/AD53 -> 0.069768272
A56: Gesamtergebnis mit Wertsteigerung Immo + BAV | E56: =E34+E39+E42+E46+E49 -> 378294.9 | F56: =F34+F39+F42+F46+F49 -> 432531.64 | G56: =G34+G39+G42+G46+G49 -> 488970.16 | H56: =H34+H39+H42+H46+H49 -> 548427.31 | I56: =I34+I39+I42+I46+I49 -> 611228.75 | J56: =J34+J39+J42+J46+J49 -> 677577.06 | K56: =K34+K39+K42+K46+K49 -> 747687.81 | L56: =L34+L39+L42+L46+L49 -> 821790.32 | ... AE56: =AE34+AE39+AE42+AE46+AE49 -> 3287430.3
A57: Inflationsbereinigt | D57: =D53*(0.98)^(COLUMN()-COLUMN($D$57)+1) -> 299390.98 | E57: =E53*(0.98)^(COLUMN()-COLUMN($D$57)+1) -> 356399.54 | F57: =F53*(0.98)^(COLUMN()-COLUMN($D$57)+1) -> 400183.2 | G57: =G53*(0.98)^(COLUMN()-COLUMN($D$57)+1) -> 444101.15 | H57: =H53*(0.98)^(COLUMN()-COLUMN($D$57)+1) -> 488828.27 | I57: =I53*(0.98)^(COLUMN()-COLUMN($D$57)+1) -> 534548.51 | J57: =J53*(0.98)^(COLUMN()-COLUMN($D$57)+1) -> 581320.89 | K57: =K53*(0.98)^(COLUMN()-COLUMN($D$57)+1) -> 629206.84 | ... AE57: =AE53*(0.98)^(COLUMN()-COLUMN($D$57)+1) -> 1860338.8
A58: Inflationskosten (jährl.) | E58: =(E53-E57)-(D53-D57) -> 8585.338 | F58: =(F53-F57)-(E53-E57) -> 10309.077 | G58: =(G53-G57)-(F53-F57) -> 12373.687 | H58: =(H53-H57)-(G53-G57) -> 14580.225 | I58: =(I53-I57)-(H53-H57) -> 16928.382 | J58: =(J53-J57)-(I53-I57) -> 19420.063 | K58: =(K53-K57)-(J53-J57) -> 22065.807 | L58: =(L53-L57)-(K53-K57) -> 24876.885 | ... AE58: =(AE53-AE57)-(AD53-AD57) -> 127776.45
C60: Rendite Wohnung | D60: =S45-B45 -> 124512.6 | E60: =(D60/B45) -> 0.34586834
C61: Redite Aktiien | D61: =S39-B38 -> 652547.96 | E61: =D61/S39 -> 0.86184999 | R61: GesamtV | S61: =SUM(S45,S39-P65,S34) -> 1208453.2
N64: Gewinn | O64: Gewinn n. Steuer | P64: Steuer
D65: Miete | E65: Einnahmen 15 Jahre | N65: =S39-S38 -> 380629.38 | O65: =N65*0.75 -> 285472.04 | P65: =N65-O65 -> 95157.345
D66: 650 | E66: =D66*12*15 -> 117000
D67: KNK | E67: 21500
D68: Zinsen | E68: 85000
D69: Überschuss | E69: =E66-E67-E68 -> 10500
D72: Miete | E72: Einnahmen 15 Jahre
D73: 850 | E73: =D73*12*15 -> 153000
D74: KNK | E74: 21500
D75: Zinsen | E75: 85000
D76: Überschuss | E76: =E73-E74-E75 -> 46500

Sheet (SOLL) Prognosekurve (mit AVD)
A1: Kalkulation Wohnungskauf
A4: Kaufpreis | B4: 322000 | N4: Rate | O4: 1350 | P4: 1350
A5: Stellplätze (2 Stück) | B5: 38000 | N5: NK | O5: 80 | P5: 80
A6: Nebenkosten 10% | B6: 19800 | N6: Entfall Zinsen | O6: 140 | P6: 140
A7: Kosten Gesamt | B7: =SUM(B4:B6) -> 379800 | N7: Mehrbelastung | O7: =SUM(O4:O6) -> 1570 | P7: =SUM(P4:P6) -> 1570
N8: Miete | O8: 650 | P8: 650
A9: EK | B9: 92000 | N9: Reduz. Aktie | O9: 300 | P9: 300
A10: Kredit | B10: =B7-B9 -> 287800 | N10: Reduz. Auto | O10: 240 | P10: 240
A11: Kredit Bank | B11: 0.0348 | N11: BAV | O11: 70 | P11: 70
A12: Rate | B12: 1350 | N12: Lohnlus 2026 | O12: 150
A13: Mieteinnahmen ab 01.06.2026 | B13: 650
A14: geschätzter Überschuss/ Jahr | B14: 32000 | N14: Steuereffekt | O14: 75
A15: Aktienkauf jährlich (600 mtl.) | B15: =600*12 -> 7200 | M15: abs. Mehrbelastung mtl. | O15: =O7-SUM(O8:O14) -> 85 | P15: =P7-SUM(P8:P14) -> 310
A16: Jährlicher Überschuss nach Aktienkauf | B16: =B14-B15 -> 24800 | M16: abs. Mehrbelastung jährlich | O16: =O15*12 -> 1020 | P16: =P15*12 -> 3720
A17: Jährliche Sondertilgung | B17: 10000
A18: Überschuss | B18: =B16-B17 -> 14800 | C18: Risikoabschlag | D18: ='Haushalt (Cash)'!G38 -> 11950
A19: Rendite Depot | B19: 1.07
A20: Rendite BMW AV | B20: 1.05
A28: Sparkonto | B28: 116000
A29: Depot | B29: 104600
A31: Alter | E31: 37 | F31: 38 | G31: 39 | H31: 40 | I31: 41 | J31: 42 | K31: 43 | L31: 44 | M31: 45 | N31: 46 | O31: 47 | P31: 48 | Q31: 49 | R31: 50 | S31: 51 | T31: 52 | U31: 53 | V31: 54 | W31: 55 | X31: 56 | Y31: 57 | Z31: 58 | AA31: 59 | AB31: 60 | AC31: 61 | AD31: 62 | AE31: 63
E32: 1 | F32: 2 | G32: 3 | H32: 4 | I32: 5 | J32: 6 | K32: 7 | L32: 8 | M32: 9 | N32: 10 | O32: 11 | P32: 12 | Q32: 13 | R32: 14 | S32: 15 | T32: 16 | U32: 17 | V32: 18 | W32: 19 | X32: 20 | Y32: 21 | Z32: 22 | AA32: 23 | AB32: 24 | AC32: 25 | AD32: 26 | AE32: 27
B33: 2025 | C33: 2025 n.K. | D33: Ende 2025 | E33: Ende 2026 | F33: Ende 2027 | G33: Ende 2028 | H33: Ende 2029 | I33: Ende 2030 | J33: Ende 2031 | K33: Ende 2032 | L33: Ende 2033 | M33: Ende 2034 | N33: Ende 2035 | O33: Ende 2036 | P33: Ende 2037 | Q33: Ende 2038 | R33: Ende 2039 | S33: Ende 2040 | T33: Ende 2041 | U33: Ende 2042 | V33: Ende 2043 | W33: Ende 2044 | X33: Ende 2045 | Y33: Ende 2046 | Z33: Ende 2047 | AA33: Ende 2048 | AB33: Ende 2049 | AC33: Ende 2050 | AD33: Ende 2051 | AE33: Ende 2052
A34: Sparkonto | B34: =B28 -> 116000 | C34: =B34-B9 -> 24000 | D34: 30000 | E34: ='Haushalt (Cash)'!C7 -> 47934 | F34: =E34+$D18 -> 59884 | G34: =F34-F35+$D18 -> 65550 | H34: =G34-G35+$D18 -> 65550 | I34: =H34-H35+$D18 -> 65550 | J34: =I34-I35+$D18 -> 65550 | K34: =J34-J35+$D18 -> 65550 | L34: =K34-K35+$D18 -> 65550 | M34: =L34-L35+$D18 -> 65550 | N34: =M34-M35+$D18 -> 65550 | ... AE34: =AD34-AD35+$D18 -> 65550
A35: Überschuss Grenze 50K | F35: =F34-50000-(12*300) -> 6284 | G35: =G34-50000-(12*300) -> 11950 | H35: =H34-50000-(12*300) -> 11950 | I35: =I34-50000-(12*300) -> 11950 | J35: =J34-50000-(12*300) -> 11950 | K35: =K34-50000-(12*300) -> 11950 | L35: =L34-50000-(12*300) -> 11950 | M35: =M34-50000-(12*300) -> 11950 | ... AE35: =AE34-50000-(12*300) -> 11950
A36: Tilgunsendeüberschuss | S36: =1350*9 -> 12150 | T36: =1350*12 -> 16200 | U36: =1350*12 -> 16200 | V36: =1350*12 -> 16200 | W36: =1350*12 -> 16200 | X36: =1350*12 -> 16200 | Y36: =1350*12 -> 16200 | Z36: =1350*12 -> 16200 | AA36: =1350*12 -> 16200 | ... AE36: =1350*12 -> 16200
A38: Depot ohne Rendite | B38: 104600 | D38: =D39/1.07 -> 115234.58 | E38: =D38+B15 -> 122434.58 | F38: =E38+B15 -> 129634.58 | G38: =F38+$B15+F35 -> 143118.58 | H38: =G38+$B15+G35 -> 162268.58 | I38: =H38+$B15+H35 -> 181418.58 | J38: =I38+$B15+I35 -> 200568.58 | K38: =J38+$B15+J35 -> 219718.58 | L38: =K38+$B15+K35 -> 238868.58 | M38: =L38+$B15+L35 -> 258018.58 | N38: =M38+$B15+M35 -> 277168.58 | ... S38: =R38+$B15+R35 -> 372918.58 | T38: =S38+$B15+S35+S36 -> 404218.58 | U38: =T38+$B15+T35+T36 -> 439568.58 | V38: =U38+$B15+U35+U36 -> 474918.58 | W38: =V38+$B15+V35+V36 -> 510268.58 | X38: =W38+$B15+W35+W36 -> 545618.58 | Y38: =X38+$B15+X35+X36 -> 580968.58 | Z38: =Y38+$B15+Y35+Y36 -> 616318.58 | AA38: =Z38+$B15+Z35+Z36 -> 651668.58 | ... AE38: =AD38+$B15+AD35+AD36 -> 793068.58
A39: Depot mit Rendite | D39: 123301 | E39: =(D39*$B19)+$B15 -> 139132.07 | F39: =(E39*$B19)+$B15 -> 156071.31 | G39: =(F39*$B19)+$B15+F35 -> 180480.31 | H39: =(G39*$B19)+$B15+G35 -> 212263.93 | I39: =(H39*$B19)+$B15+H35 -> 246272.4 | J39: =(I39*$B19)+$B15+I35 -> 282661.47 | K39: =(J39*$B19)+$B15+J35 -> 321597.77 | L39: =(K39*$B19)+$B15+K35 -> 363259.62 | M39: =(L39*$B19)+$B15+L35 -> 407837.79 | N39: =(M39*$B19)+$B15+M35 -> 455536.44 | ... S39: =(R39*$B19)+$B15+R35 -> 749040.07 | T39: =(S39*$B19)+$B15+S35+S36 -> 832772.88 | U39: =(T39*$B19)+$B15+T35+T36 -> 926416.98 | V39: =(U39*$B19)+$B15+U35+U36 -> 1026616.2 | W39: =(V39*$B19)+$B15+V35+V36 -> 1133829.3 | X39: =(W39*$B19)+$B15+W35+W36 -> 1248547.3 | Y39: =(X39*$B19)+$B15+X35+X36 -> 1371295.7 | Z39: =(Y39*$B19)+$B15+Y35+Y36 -> 1502636.4 | AA39: =(Z39*$B19)+$B15+Z35+Z36 -> 1643170.9 | ... AE39: =(AD39*$B19)+$B15+AD35+AD36 -> 2310813.8
A40: jährliche Depotmehrung | E40: =E39-D39 -> 15831.07 | F40: =F39-E39 -> 16939.245 | G40: =G39-F39 -> 24408.992 | H40: =H39-G39 -> 31783.621 | I40: =I39-H39 -> 34008.475 | J40: =J39-I39 -> 36389.068 | K40: =K39-J39 -> 38936.303 | L40: =L39-K39 -> 41661.844 | ... AE40: =AE39-AD39 -> 184212.12
A42: Wohnung Besitzanteil | D42: 62200 | E42: =SUM(TilgungsRechner!E13:E19,TilgungsRechner!G15)+D42+10000 -> 85433.83 | F42: =SUM(TilgungsRechner!E20:E32,TilgungsRechner!G27,TilgungsRechner!G28)+E42 -> 102307.57 | G42: =SUM(TilgungsRechner!E33:E45,TilgungsRechner!G41)+'(SOLL) Prognosekurve (mit AVD)'!F42 -> 119777.98 | H42: =SUM(TilgungsRechner!E46:E58,TilgungsRechner!G54)+G42 -> 137866.15 | I42: =SUM(TilgungsRechner!E59:E71,TilgungsRechner!G67)+H42 -> 156593.93 | J42: =SUM(TilgungsRechner!E72:E84,TilgungsRechner!G80)+I42 -> 175983.93 | K42: =SUM(TilgungsRechner!E85:E97,TilgungsRechner!G93)+J42 -> 196059.56 | L42: =SUM(TilgungsRechner!E98:E110,TilgungsRechner!G106)+K42 -> 216845.09 | M42: =SUM(TilgungsRechner!E111:E123,TilgungsRechner!G119)+L42 -> 238365.59 | N42: =SUM(TilgungsRechner!E124:E136,TilgungsRechner!G132)+M42 -> 260647.07 | O42: =SUM(TilgungsRechner!E137:E149,TilgungsRechner!G145)+N42 -> 283716.44 | P42: =SUM(TilgungsRechner!E150:E162,TilgungsRechner!G157,TilgungsRechner!G158)+O42 -> 307601.55 | Q42: =SUM(TilgungsRechner!E163:E175,TilgungsRechner!G171)+P42 -> 332331.25 | R42: =SUM(TilgungsRechner!E176:E188,TilgungsRechner!G184)+Q42 -> 357935.4 | S42: =SUM(TilgungsRechner!E189:E190)+R42 -> 360628.16 | T42: 360000 | U42: =SUM(TilgungsRechner!G189:G190)+T42 -> 360000 | V42: =SUM(TilgungsRechner!H189:H190)+U42 -> 360000 | W42: 360000 | X42: 360000 | Y42: 360000 | Z42: 360000 | AA42: 360000 | AB42: 360000 | AC42: 360000 | AD42: 360000 | AE42: 360000
A43: Prozentualer Anteil | D43: =D42/360000 -> 0.17277778 | E43: =E42/360000 -> 0.23731619 | F43: =F42/360000 -> 0.28418771 | G43: =G42/360000 -> 0.33271662 | H43: =H42/360000 -> 0.38296153 | I43: =I42/360000 -> 0.43498313 | J43: =J42/360000 -> 0.48884424 | K43: =K42/360000 -> 0.5446099 | ... AE43: =AE42/360000 -> 1
A45: Wohnung Wert | B45: 360000 | C45: 1.02 | D45: 360000 | E45: =D45*$C45 -> 367200 | F45: =E45*$C45 -> 374544 | G45: =F45*$C45 -> 382034.88 | H45: =G45*$C45 -> 389675.58 | I45: =H45*$C45 -> 397469.09 | J45: =I45*$C45 -> 405418.47 | K45: =J45*$C45 -> 413526.84 | L45: =K45*$C45 -> 421797.38 | ... AE45: =AD45*$C45 -> 614479.13
A46: jährliche Wertsteigerung | E46: =E45-D45 -> 7200 | F46: =F45-E45 -> 7344 | G46: =G45-F45 -> 7490.88 | H46: =H45-G45 -> 7640.6976 | I46: =I45-H45 -> 7793.5116 | J46: =J45-I45 -> 7949.3818 | K46: =K45-J45 -> 8108.3694 | L46: =L45-K45 -> 8270.5368 | ... AE46: =AE45-AD45 -> 12048.61
A48: Altersvorsorge BMW ohne Rendite | D48: 85000 | E48: =91500+(200*7)+1000 -> 93900 | F48: =E48+(200*12)+800 -> 97100 | G48: =F48+(200*12)+800 -> 100300 | H48: =G48+(200*12)+800 -> 103500 | I48: =H48+(200*12)+800 -> 106700 | J48: =I48+(200*12)+800 -> 109900 | K48: =J48+(200*12)+800 -> 113100 | L48: =K48+(200*12)+800 -> 116300 | M48: =L48+(200*12)+800 -> 119500 | ... AE48: =AD48+(200*12)+800 -> 177100
A49: Altersvorsorge BMW mit Rendite | D49: 90000 | E49: =E48*$B$20 -> 98595 | F49: =E49*$B$20+(12*200)+1000 -> 106924.75 | G49: =F49*$B$20+(12*200)+1000 -> 115670.99 | H49: =G49*$B$20+(12*200)+1000 -> 124854.54 | I49: =H49*$B$20+(12*200)+1000 -> 134497.26 | J49: =I49*$B$20+(12*200)+1000 -> 144622.13 | K49: =J49*$B$20+(12*200)+1000 -> 155253.23 | L49: =K49*$B$20+(12*200)+1000 -> 166415.89 | M49: =L49*$B$20+(12*200)+1000 -> 178136.69 | ... AE49: =AD49*$B$20+(12*200)+1000 -> 524357.29
A51: Altersvorsorge Bund ohne Rendite | F51: =300*12+1680 -> 5280 | G51: =F51+(300*12+1680) -> 10560 | H51: =G51+(300*12+1680) -> 15840 | I51: =H51+(300*12+1680) -> 21120 | J51: =I51+(300*12+1680) -> 26400 | K51: =J51+(300*12+1680) -> 31680 | L51: =K51+(300*12+1680) -> 36960 | M51: =L51+(300*12+1680) -> 42240 | N51: =M51+(300*12+1680) -> 47520 | ... AE51: =AD51+(300*12+1680) -> 137280
A52: Altersvorsorge Bund mit Rendite | F52: =F51*$B$19 -> 5649.6 | G52: =F52*$B$19+(300*12+1680) -> 11325.072 | H52: =G52*$B$19+(300*12+1680) -> 17397.827 | I52: =H52*$B$19+(300*12+1680) -> 23895.675 | J52: =I52*$B$19+(300*12+1680) -> 30848.372 | K52: =J52*$B$19+(300*12+1680) -> 38287.758 | L52: =K52*$B$19+(300*12+1680) -> 46247.901 | M52: =L52*$B$19+(300*12+1680) -> 54765.254 | N52: =M52*$B$19+(300*12+1680) -> 63878.822 | ... AE52: =AD52*$B$19+(300*12+1680) -> 364617.74
A54: Gesamtergebnis ohne BMW AV | D54: =D34+D39+D42 -> 215501 | E54: =E34+E39+E42 -> 272499.9 | F54: =F34+F39+F42 -> 318262.89 | G54: =G34+G39+G42 -> 365808.29 | H54: =H34+H39+H42 -> 415680.08 | I54: =I34+I39+I42 -> 468416.33 | J54: =J34+J39+J42 -> 524195.4 | K54: =K34+K39+K42 -> 583207.34 | ... AE54: =AE34+AE39+AE42 -> 2736363.8
A55: Gesamtergebnis mit Wertsteigerung Immo | E55: =E34+E39+E42+E46 -> 279699.9 | F55: =F34+F39+F42+F46 -> 325606.89 | G55: =G34+G39+G42+G46 -> 373299.17 | H55: =H34+H39+H42+H46 -> 423320.78 | I55: =I34+I39+I42+I46 -> 476209.84 | J55: =J34+J39+J42+J46 -> 532144.78 | K55: =K34+K39+K42+K46 -> 591315.71 | L55: =L34+L39+L42+L46 -> 653925.24 | ... AE55: =AE34+AE39+AE42+AE46 -> 2748412.5
A56: Gesamtergebnis | D56: =D34+D39+D42+D49 -> 305501 | E56: =E34+E39+E42+E49 -> 371094.9 | F56: =F34+F39+F42+F49 -> 425187.64 | G56: =G34+G39+G42+G49 -> 481479.28 | H56: =H34+H39+H42+H49 -> 540534.62 | I56: =I34+I39+I42+I49 -> 602913.59 | J56: =J34+J39+J42+J49 -> 668817.52 | K56: =K34+K39+K42+K49 -> 738460.57 | ... AE56: =AE34+AE39+AE42+AE49 -> 3260721.1
A57: Vermögenssteigerung in € | E57: =E56-D56 -> 65593.9 | F57: =F56-E56 -> 54092.74 | G57: =G56-F56 -> 56291.638 | H57: =H56-G56 -> 59055.341 | I57: =I56-H56 -> 62378.978 | J57: =J56-I56 -> 65903.93 | K57: =K56-J56 -> 69643.047 | L57: =L56-K56 -> 73610.027 | ... AE57: =AE56-AD56 -> 212419.61
A58: Vermögenssteigerung in % | E58: =E57/D56 -> 0.21470928 | F58: =F57/E56 -> 0.14576525 | G58: =G57/F56 -> 0.13239246 | H58: =H57/G56 -> 0.12265396 | I58: =I57/H56 -> 0.11540237 | J58: =J57/I56 -> 0.10930908 | K58: =K57/J56 -> 0.10412862 | L58: =L57/K56 -> 0.099680376 | ... AE58: =AE57/AD56 -> 0.06968458
A59: Gesamtergebnis mit Wertsteigerung Immo + BAV + AVD | E59: =E34+E39+E42+E46+E49 -> 378294.9 | F59: =F34+F39+F42+F46+F49+F52 -> 438181.24 | G59: =G34+G39+G42+G46+G49+G52 -> 500295.23 | H59: =H34+H39+H42+H46+H49+H52 -> 565573.14 | I59: =I34+I39+I42+I46+I49+I52 -> 634602.78 | J59: =J34+J39+J42+J46+J49+J52 -> 707615.28 | K59: =K34+K39+K42+K46+K49+K52 -> 784856.7 | L59: =L34+L39+L42+L46+L49+L52 -> 866589.04 | M59: =M34+M39+M42+M46+M49+M52 -> 953091.28 | ... AE59: =AE34+AE39+AE42+AE46+AE49+AE52 -> 3637387.5
A60: Inflationsbereinigt | D60: =D56*(0.98)^(COLUMN()-COLUMN($D$60)+1) -> 299390.98 | E60: =E56*(0.98)^(COLUMN()-COLUMN($D$60)+1) -> 356399.54 | F60: =F56*(0.98)^(COLUMN()-COLUMN($D$60)+1) -> 400183.2 | G60: =G56*(0.98)^(COLUMN()-COLUMN($D$60)+1) -> 444101.15 | H60: =H56*(0.98)^(COLUMN()-COLUMN($D$60)+1) -> 488600.48 | I60: =I56*(0.98)^(COLUMN()-COLUMN($D$60)+1) -> 534086.41 | J60: =J56*(0.98)^(COLUMN()-COLUMN($D$60)+1) -> 580617.57 | K60: =K56*(0.98)^(COLUMN()-COLUMN($D$60)+1) -> 628254.95 | ... AE60: =AE56*(0.98)^(COLUMN()-COLUMN($D$60)+1) -> 1852011.9
A61: Inflationskosten (jährl.) | E61: =(E56-E60)-(D56-D60) -> 8585.338 | F61: =(F56-F60)-(E56-E60) -> 10309.077 | G61: =(G56-G60)-(F56-F60) -> 12373.687 | H61: =(H56-H60)-(G56-G60) -> 14556.013 | I61: =(I56-I60)-(H56-H60) -> 16893.045 | J61: =(J56-J60)-(I56-I60) -> 19372.774 | K61: =(K56-K60)-(J56-J60) -> 22005.669 | L61: =(L56-L60)-(K56-K60) -> 24802.931 | ... AE61: =(AE56-AE60)-(AD56-AD60) -> 127104.26
C63: Rendite Wohnung | D63: =S45-B45 -> 124512.6 | E63: =(D63/B45) -> 0.34586834
C64: Redite Aktiien | D64: =S39-B38 -> 644440.07 | E64: =D64/S39 -> 0.8603546 | R64: GesamtV | S64: =SUM(S45,S39-P68,S34) -> 1205072.3
N67: Gewinn | O67: Gewinn n. Steuer | P67: Steuer
D68: Miete | E68: Einnahmen 15 Jahre | N68: =S39-S38 -> 376121.49 | O68: =N68*0.75 -> 282091.12 | P68: =N68-O68 -> 94030.373
D69: 650 | E69: =D69*12*15 -> 117000
D70: KNK | E70: 21500
D71: Zinsen | E71: 85000
D72: Überschuss | E72: =E69-E70-E71 -> 10500
D75: Miete | E75: Einnahmen 15 Jahre
D76: 850 | E76: =D76*12*15 -> 153000
D77: KNK | E77: 21500
D78: Zinsen | E78: 85000
D79: Überschuss | E79: =E76-E77-E78 -> 46500

Sheet TilgungsRechner
A1: Jahre | B1: Datum | C1: Restschuld | D1: Zins | E1: Tilgung | F1: Rate | G1: Sonderzahlung | H1: Sonderkosten | I1: Mieteinnahmen | J1: Tilgung [Jahr] | K1: Netto Zins Überschuss [Jahr] | L1: Abschreibung Küche | M1: Steuerersparnis Wohnung [netto] | N1: Casflow [mtl] | O1: Casflow [Jahr] | P1: netto Vermögens-steigerung [Jahr] | Q1: ROI dyn | R1: Wertsteigerung Immobilie | S1: Ergebnis [Jahr] | T1: Zinssatz | U1: effektive Steuerlast | V1: EK | W1: Wertsteigerung
T2: 0.0348 | U2: 0.4 | V2: 92000 | W2: 0.018
B3: 45901 | G3: =V2-H3 -> 74338.8 | H3: 17661.2 | N3: =-H3 -> -17661.2
B4: 45931 | D4: 548.58 | E4: 0 | F4: 548.58 | N4: -548.58
B5: 45962 | D5: 623.5 | E5: 0 | F5: 623.5 | N5: -623.5
B6: 45992 | D6: 623.5 | E6: 0 | F6: 623.5 | J6: =V2-H3 -> 74338.8 | K6: =0-SUM(D3:D6) -> -1795.58 | M6: 533 | N6: -623.5 | O6: =SUM(N3:N6)+M6 -> -18923.78 | P6: =K6+M6-H3 -> -18923.78 | Q6: =P6/J6 -> -0.25456128 | S6: =P6 -> -18923.78
B7: 46023 | D7: 623.5 | E7: 0 | F7: 623.5 | H7: 4000 | N7: -4623.5
B8: 46054 | D8: 623.5 | E8: 0 | F8: 623.5 | N8: =H8-D8 -> -623.5
B9: 46082 | D9: 623.5 | E9: 0 | F9: 623.5 | N9: =I9-D9 -> -623.5
B10: 46113 | D10: 623.5 | E10: =F10-D10 -> 0 | F10: 623.5 | N10: =I10-D10 -> -623.5
B11: 46143 | D11: 623.5 | E11: =F11-D11 -> 0 | F11: 623.5 | N11: =I11-D11 -> -623.5
B12: 46174 | D12: 630.75 | E12: 0 | F12: 630.75 | H12: 3000 | N12: =I12-D12-H12 -> -3630.75
B13: 46204 | C13: 288000 | D13: =(C13*T$2)/12 -> 835.2 | E13: =F13-D13 -> 515.8 | F13: 1351 | I13: 650 | N13: =I13-D13 -> -185.2
B14: 46235 | C14: =C13-E13 -> 287484.2 | D14: =(C14*T$2)/12 -> 833.70418 | E14: =F14-D14 -> 517.29582 | F14: 1351 | I14: 650 | N14: =I14-D14 -> -183.70418
B15: 46265 | C15: =C14-E14 -> 286966.9 | D15: 0 | E15: 0 | F15: 0 | G15: 10000 | N15: =D15-G15 -> -10000
B16: 46266 | C16: =C15-G15 -> 276966.9 | D16: =(C16*T$2)/12 -> 803.20402 | E16: =F16-D16 -> 547.79598 | F16: 1351 | I16: 650 | N16: =I16-D16 -> -153.20402
B17: 46296 | C17: =C16-E16 -> 276419.11 | D17: =(C17*T$2)/12 -> 801.61541 | E17: =F17-D17 -> 549.38459 | F17: 1351 | I17: 650 | N17: =I17-D17 -> -151.61541
B18: 46327 | C18: =C17-E17 -> 275869.72 | D18: =(C18*T$2)/12 -> 800.0222 | E18: =F18-D18 -> 550.9778 | F18: 1351 | I18: 650 | N18: =I18-D18 -> -150.0222
A19: 1 | B19: 46357 | C19: =C18-E18 -> 275318.75 | D19: =(C19*T$2)/12 -> 798.42436 | E19: =F19-D19 -> 552.57564 | F19: 1351 | I19: 650 | J19: =SUM(E7:E19)+G15 -> 13233.83 | K19: =SUM(I7:I19)-SUM(D7:D19) -> -4720.4202 | L19: 230 | M19: 3040 | N19: =I19-D19 -> -148.42436 | O19: =SUM(N7:N19)+L19+M19 -> -18450.42 | P19: =K19+L19+M19-H7-H12 -> -8450.4202 | Q19: =P19/J19 -> -0.63854684 | R19: =C$222 * W$2 -> 6480 | S19: =P19+R19 -> -1970.4202
B20: 46388 | C20: =C19-E19 -> 274766.17 | D20: =(C20*T$2)/12 -> 796.82189 | E20: =F20-D20 -> 554.17811 | F20: 1351 | I20: 650 | N20: =I20-D20 -> -146.82189
B21: 46419 | C21: =C20-E20 -> 274211.99 | D21: =(C21*T$2)/12 -> 795.21478 | E21: =F21-D21 -> 555.78522 | F21: 1351 | I21: 650 | N21: =I21-D21 -> -145.21478
B22: 46447 | C22: =C21-E21 -> 273656.21 | D22: =(C22*T$2)/12 -> 793.603 | E22: =F22-D22 -> 557.397 | F22: 1351 | I22: 650 | N22: =I22-D22 -> -143.603
B23: 46478 | C23: =C22-E22 -> 273098.81 | D23: =(C23*T$2)/12 -> 791.98655 | E23: =F23-D23 -> 559.01345 | F23: 1351 | I23: 650 | N23: =I23-D23 -> -141.98655
B24: 46508 | C24: =C23-E23 -> 272539.8 | D24: =(C24*T$2)/12 -> 790.36541 | E24: =F24-D24 -> 560.63459 | F24: 1351 | I24: 650 | N24: =I24-D24 -> -140.36541
B25: 46539 | C25: =C24-E24 -> 271979.16 | D25: =(C25*T$2)/12 -> 788.73957 | E25: =F25-D25 -> 562.26043 | F25: 1351 | I25: 650 | N25: =I25-D25 -> -138.73957
B26: 46569 | C26: =C25-E25 -> 271416.9 | D26: =(C26*T$2)/12 -> 787.10901 | E26: =F26-D26 -> 563.89099 | F26: 1351 | I26: 650 | N26: =I26-D26 -> -137.10901
B27: 46600 | C27: =C26-E26 -> 270853.01 | D27: =(C27*T$2)/12 -> 785.47373 | E27: =F27-D27 -> 565.52627 | F27: 1351 | I27: 650 | N27: =I27-D27 -> -135.47373
B28: 46630 | C28: =C27-E27 -> 270287.48 | D28: 0 | E28: 0 | F28: 0 | G28: ='Haushalt (Cash)'!$G$28 -> 10000 | N28: =D28-G28 -> -10000
B29: 46631 | C29: =C28-G28 -> 260287.48 | D29: =(C29*T$2)/12 -> 754.8337 | E29: =F29-D29 -> 596.1663 | F29: 1351 | I29: 650 | N29: =I29-D29 -> -104.8337
B30: 46661 | C30: =C29-E29 -> 259691.32 | D30: =(C30*T$2)/12 -> 753.10482 | E30: =F30-D30 -> 597.89518 | F30: 1351 | I30: 650 | N30: =I30-D30 -> -103.10482
B31: 46692 | C31: =C30-E30 -> 259093.42 | D31: =(C31*T$2)/12 -> 751.37093 | E31: =F31-D31 -> 599.62907 | F31: 1351 | I31: 650 | N31: =I31-D31 -> -101.37093
A32: 2 | B32: 46722 | C32: =C31-E31 -> 258493.79 | D32: =(C32*T$2)/12 -> 749.632 | E32: =F32-D32 -> 601.368 | F32: 1351 | I32: 650 | J32: =SUM(E20:E32)+G28 -> 16873.745 | K32: =SUM(I20:I32)-SUM(D20:D32) -> -1538.2554 | L32: 230 | M32: 2500 | N32: =I32-D32 -> -99.632001 | O32: =SUM(N20:N32)+L32+M32 -> -8808.2554 | P32: =K32+L32+M32 -> 1191.7446 | Q32: =P32/J32 -> 0.070627157 | R32: =(C$222 + R19) * W$2 -> 6596.64 | S32: =P32+R32 -> 7788.3846
B33: 46753 | C33: =C32-E32 -> 257892.43 | D33: =(C33*T$2)/12 -> 747.88803 | E33: =F33-D33 -> 603.11197 | F33: 1351 | I33: 650 | N33: =I33-D33 -> -97.888034
B34: 46784 | C34: =C33-E33 -> 257289.31 | D34: =(C34*T$2)/12 -> 746.13901 | E34: =F34-D34 -> 604.86099 | F34: 1351 | I34: 650 | N34: =I34-D34 -> -96.139009
B35: 46813 | C35: =C34-E34 -> 256684.45 | D35: =(C35*T$2)/12 -> 744.38491 | E35: =F35-D35 -> 606.61509 | F35: 1351 | I35: 650 | N35: =I35-D35 -> -94.384913
B36: 46844 | C36: =C35-E35 -> 256077.84 | D36: =(C36*T$2)/12 -> 742.62573 | E36: =F36-D36 -> 608.37427 | F36: 1351 | I36: 650 | N36: =I36-D36 -> -92.625729
B37: 46874 | C37: =C36-E36 -> 255469.46 | D37: =(C37*T$2)/12 -> 740.86144 | E37: =F37-D37 -> 610.13856 | F37: 1351 | I37: 650 | N37: =I37-D37 -> -90.861443
B38: 46905 | C38: =C37-E37 -> 254859.32 | D38: =(C38*T$2)/12 -> 739.09204 | E38: =F38-D38 -> 611.90796 | F38: 1351 | I38: 650 | N38: =I38-D38 -> -89.092042
B39: 46935 | C39: =C38-E38 -> 254247.42 | D39: =(C39*T$2)/12 -> 737.31751 | E39: =F39-D39 -> 613.68249 | F39: 1351 | I39: 650 | N39: =I39-D39 -> -87.317509
B40: 46966 | C40: =C39-E39 -> 253633.73 | D40: =(C40*T$2)/12 -> 735.53783 | E40: =F40-D40 -> 615.46217 | F40: 1351 | I40: 650 | N40: =I40-D40 -> -85.537829
B41: 46996 | C41: =C40-E40 -> 253018.27 | D41: 0 | E41: 0 | F41: 0 | G41: ='Haushalt (Cash)'!$G$28 -> 10000 | N41: =D41-G41 -> -10000
B42: 46997 | C42: =C41-G41 -> 243018.27 | D42: =(C42*T$2)/12 -> 704.75299 | E42: =F42-D42 -> 646.24701 | F42: 1351 | I42: 650 | N42: =I42-D42 -> -54.752989
B43: 47027 | C43: =C42-E42 -> 242372.03 | D43: =(C43*T$2)/12 -> 702.87887 | E43: =F43-D43 -> 648.12113 | F43: 1351 | I43: 650 | N43: =I43-D43 -> -52.878873
B44: 47058 | C44: =C43-E43 -> 241723.9 | D44: =(C44*T$2)/12 -> 700.99932 | E44: =F44-D44 -> 650.00068 | F44: 1351 | I44: 650 | N44: =I44-D44 -> -50.999321
A45: 3 | B45: 47088 | C45: =C44-E44 -> 241073.9 | D45: =(C45*T$2)/12 -> 699.11432 | E45: =F45-D45 -> 651.88568 | F45: 1351 | I45: 650 | J45: =SUM(E33:E45)+G41 -> 17470.408 | K45: =SUM(I33:I45)-SUM(D33:D45) -> -941.59201 | L45: 230 | M45: 2500 | N45: =I45-D45 -> -49.114319 | O45: =SUM(N33:N45)+L45+M45 -> -8211.592 | P45: =K45+L45+M45 -> 1788.408 | Q45: =P45/J45 -> 0.10236784 | R45: =(C$222 + R19+ R32) * W$2 -> 6715.3795 | S45: =P45+R45 -> 8503.7875
B46: 47119 | C46: =C45-E45 -> 240422.02 | D46: =(C46*T$2)/12 -> 697.22385 | E46: =F46-D46 -> 653.77615 | F46: 1351 | I46: 650 | N46: =I46-D46 -> -47.223851
B47: 47150 | C47: =C46-E46 -> 239768.24 | D47: =(C47*T$2)/12 -> 695.3279 | E47: =F47-D47 -> 655.6721 | F47: 1351 | I47: 650 | N47: =I47-D47 -> -45.3279
B48: 47178 | C48: =C47-E47 -> 239112.57 | D48: =(C48*T$2)/12 -> 693.42645 | E48: =F48-D48 -> 657.57355 | F48: 1351 | I48: 650 | N48: =I48-D48 -> -43.426451
B49: 47209 | C49: =C48-E48 -> 238455 | D49: =(C49*T$2)/12 -> 691.51949 | E49: =F49-D49 -> 659.48051 | F49: 1351 | I49: 650 | N49: =I49-D49 -> -41.519488
B50: 47239 | C50: =C49-E49 -> 237795.52 | D50: =(C50*T$2)/12 -> 689.60699 | E50: =F50-D50 -> 661.39301 | F50: 1351 | I50: 650 | N50: =I50-D50 -> -39.606994
B51: 47270 | C51: =C50-E50 -> 237134.12 | D51: =(C51*T$2)/12 -> 687.68895 | E51: =F51-D51 -> 663.31105 | F51: 1351 | I51: 650 | N51: =I51-D51 -> -37.688955
B52: 47300 | C52: =C51-E51 -> 236470.81 | D52: =(C52*T$2)/12 -> 685.76535 | E52: =F52-D52 -> 665.23465 | F52: 1351 | I52: 650 | N52: =I52-D52 -> -35.765353
B53: 47331 | C53: =C52-E52 -> 235805.58 | D53: =(C53*T$2)/12 -> 683.83617 | E53: =F53-D53 -> 667.16383 | F53: 1351 | I53: 650 | N53: =I53-D53 -> -33.836172
B54: 47361 | C54: =C53-E53 -> 235138.41 | D54: 0 | E54: 0 | F54: 0 | G54: ='Haushalt (Cash)'!$G$28 -> 10000 | N54: =D54-G54 -> -10000
B55: 47362 | C55: =C54-G54 -> 225138.41 | D55: =(C55*T$2)/12 -> 652.9014 | E55: =F55-D55 -> 698.0986 | F55: 1351 | I55: 650 | N55: =I55-D55 -> -2.901397
B56: 47392 | C56: =C55-E55 -> 224440.31 | D56: =(C56*T$2)/12 -> 650.87691 | E56: =F56-D56 -> 700.12309 | F56: 1351 | I56: 650 | N56: =I56-D56 -> -0.87691101
B57: 47423 | C57: =C56-E56 -> 223740.19 | D57: =(C57*T$2)/12 -> 648.84655 | E57: =F57-D57 -> 702.15345 | F57: 1351 | I57: 650 | N57: =I57-D57 -> 1.1534459
A58: 4 | B58: 47453 | C58: =C57-E57 -> 223038.04 | D58: =(C58*T$2)/12 -> 646.81031 | E58: =F58-D58 -> 704.18969 | F58: 1351 | I58: 650 | J58: =SUM(E46:E58)+G54 -> 18088.17 | K58: =SUM(I46:I58)-SUM(D46:D58) -> -323.83033 | L58: 230 | M58: 2500 | N58: =I58-D58 -> 3.1896909 | O58: =SUM(N46:N58)+L58+M58 -> -7593.8303 | P58: =K58+L58+M58 -> 2406.1697 | Q58: =P58/J58 -> 0.1330245 | R58: =(C$222 +R19+R32+ R45) * W$2 -> 6836.2564 | S58: =P58+R58 -> 9242.426
B59: 47484 | C59: =C58-E58 -> 222333.85 | D59: =(C59*T$2)/12 -> 644.76816 | E59: =F59-D59 -> 706.23184 | F59: 1351 | I59: 650 | N59: =I59-D59 -> 5.231841
B60: 47515 | C60: =C59-E59 -> 221627.62 | D60: =(C60*T$2)/12 -> 642.72009 | E60: =F60-D60 -> 708.27991 | F60: 1351 | I60: 650 | N60: =I60-D60 -> 7.2799134
B61: 47543 | C61: =C60-E60 -> 220919.34 | D61: =(C61*T$2)/12 -> 640.66607 | E61: =F61-D61 -> 710.33393 | F61: 1351 | I61: 650 | N61: =I61-D61 -> 9.3339251
B62: 47574 | C62: =C61-E61 -> 220209 | D62: =(C62*T$2)/12 -> 638.60611 | E62: =F62-D62 -> 712.39389 | F62: 1351 | I62: 650 | N62: =I62-D62 -> 11.393894
B63: 47604 | C63: =C62-E62 -> 219496.61 | D63: =(C63*T$2)/12 -> 636.54016 | E63: =F63-D63 -> 714.45984 | F63: 1351 | I63: 650 | N63: =I63-D63 -> 13.459836
B64: 47635 | C64: =C63-E63 -> 218782.15 | D64: =(C64*T$2)/12 -> 634.46823 | E64: =F64-D64 -> 716.53177 | F64: 1351 | I64: 650 | N64: =I64-D64 -> 15.531769
B65: 47665 | C65: =C64-E64 -> 218065.62 | D65: =(C65*T$2)/12 -> 632.39029 | E65: =F65-D65 -> 718.60971 | F65: 1351 | I65: 650 | N65: =I65-D65 -> 17.609711
B66: 47696 | C66: =C65-E65 -> 217347.01 | D66: =(C66*T$2)/12 -> 630.30632 | E66: =F66-D66 -> 720.69368 | F66: 1351 | I66: 650 | N66: =I66-D66 -> 19.69368
B67: 47726 | C67: =C66-E66 -> 216626.31 | D67: 0 | E67: 0 | F67: 0 | G67: ='Haushalt (Cash)'!$G$28 -> 10000 | N67: =D67-G67 -> -10000
B68: 47727 | C68: =C67-G67 -> 206626.31 | D68: =(C68*T$2)/12 -> 599.21631 | E68: =F68-D68 -> 751.78369 | F68: 1351 | I68: 650 | N68: =I68-D68 -> 50.783691
B69: 47757 | C69: =C68-E68 -> 205874.53 | D69: =(C69*T$2)/12 -> 597.03614 | E69: =F69-D69 -> 753.96386 | F69: 1351 | I69: 650 | N69: =I69-D69 -> 52.963864
B70: 47788 | C70: =C69-E69 -> 205120.57 | D70: =(C70*T$2)/12 -> 594.84964 | E70: =F70-D70 -> 756.15036 | F70: 1351 | I70: 650 | N70: =I70-D70 -> 55.150359
A71: 5 | B71: 47818 | C71: =C70-E70 -> 204364.42 | D71: =(C71*T$2)/12 -> 592.6568 | E71: =F71-D71 -> 758.3432 | F71: 1351 | I71: 650 | J71: =SUM(E59:E71)+G67 -> 18727.776 | K71: =SUM(I59:I71)-SUM(D59:D71) -> 315.77568 | L71: 230 | M71: 2500 | N71: =I71-D71 -> 57.343195 | O71: =SUM(N59:N71)+L71+M71 -> -6954.2243 | P71: =K71+L71+M71 -> 3045.7757 | Q71: =P71/J71 -> 0.16263414 | R71: =(C$222 +R19 +R32+R45+ R58) * W$2 -> 6959.309 | S71: =P71+R71 -> 10005.085
B72: 47849 | C72: =C71-E71 -> 203606.07 | D72: =(C72*T$2)/12 -> 590.45761 | E72: =F72-D72 -> 760.54239 | F72: 1351 | I72: 650 | N72: =I72-D72 -> 59.542391
B73: 47880 | C73: =C72-E72 -> 202845.53 | D73: =(C73*T$2)/12 -> 588.25204 | E73: =F73-D73 -> 762.74796 | F73: 1351 | I73: 650 | N73: =I73-D73 -> 61.747963
B74: 47908 | C74: =C73-E73 -> 202082.78 | D74: =(C74*T$2)/12 -> 586.04007 | E74: =F74-D74 -> 764.95993 | F74: 1351 | I74: 650 | N74: =I74-D74 -> 63.959933
B75: 47939 | C75: =C74-E74 -> 201317.82 | D75: =(C75*T$2)/12 -> 583.82168 | E75: =F75-D75 -> 767.17832 | F75: 1351 | I75: 650 | N75: =I75-D75 -> 66.178316
B76: 47969 | C76: =C75-E75 -> 200550.64 | D76: =(C76*T$2)/12 -> 581.59687 | E76: =F76-D76 -> 769.40313 | F76: 1351 | I76: 650 | N76: =I76-D76 -> 68.403133
B77: 48000 | C77: =C76-E76 -> 199781.24 | D77: =(C77*T$2)/12 -> 579.3656 | E77: =F77-D77 -> 771.6344 | F77: 1351 | I77: 650 | N77: =I77-D77 -> 70.634403
B78: 48030 | C78: =C77-E77 -> 199009.61 | D78: =(C78*T$2)/12 -> 577.12786 | E78: =F78-D78 -> 773.87214 | F78: 1351 | I78: 650 | N78: =I78-D78 -> 72.872142
B79: 48061 | C79: =C78-E78 -> 198235.73 | D79: =(C79*T$2)/12 -> 574.88363 | E79: =F79-D79 -> 776.11637 | F79: 1351 | I79: 650 | N79: =I79-D79 -> 75.116372
B80: 48091 | C80: =C79-E79 -> 197459.62 | D80: 0 | E80: 0 | F80: 0 | G80: ='Haushalt (Cash)'!$G$28 -> 10000 | N80: =D80-G80 -> -10000
B81: 48092 | C81: =MAX(0,C80-G80) -> 187459.62 | D81: =(C81*T$2)/12 -> 543.63289 | E81: =F81-D81 -> 807.36711 | F81: =IF(C81=0,0,1351) -> 1351 | I81: 650 | N81: =I81-D81 -> 106.36711
B82: 48122 | C82: =C81-E81 -> 186652.25 | D82: =(C82*T$2)/12 -> 541.29153 | E82: =F82-D82 -> 809.70847 | F82: =IF(C82=0,0,1351) -> 1351 | I82: 650 | N82: =I82-D82 -> 108.70847
B83: 48153 | C83: =C82-E82 -> 185842.54 | D83: =(C83*T$2)/12 -> 538.94337 | E83: =F83-D83 -> 812.05663 | F83: =IF(C83=0,0,1351) -> 1351 | I83: 650 | N83: =I83-D83 -> 111.05663
A84: 6 | B84: 48183 | C84: =C83-E83 -> 185030.49 | D84: =(C84*T$2)/12 -> 536.58841 | E84: =F84-D84 -> 814.41159 | F84: =IF(C84=0,0,1351) -> 1351 | I84: 650 | J84: =SUM(E72:E84)+G80 -> 19389.998 | K84: =SUM(I72:I84)-SUM(D72:D84) -> 977.99846 | L84: 230 | M84: 2500 | N84: =I84-D84 -> 113.41159 | O84: =SUM(N72:N84)+L84+M84 -> -6292.0015 | P84: =K84+L84+M84 -> 3707.9985 | Q84: =P84/J84 -> 0.19123253 | R84: =(C$222 +R19 +R32 +R45+R58+ R71) * W$2 -> 7084.5765 | S84: =P84+R84 -> 10792.575
B85: 48214 | C85: =C84-E84 -> 184216.07 | D85: =(C85*T$2)/12 -> 534.22661 | E85: =F85-D85 -> 816.77339 | F85: =IF(C85=0,0,1351) -> 1351 | I85: 650 | N85: =I85-D85 -> 115.77339
B86: 48245 | C86: =C85-E85 -> 183399.3 | D86: =(C86*T$2)/12 -> 531.85797 | E86: =F86-D86 -> 819.14203 | F86: =IF(C86=0,0,1351) -> 1351 | I86: 650 | N86: =I86-D86 -> 118.14203
B87: 48274 | C87: =C86-E86 -> 182580.16 | D87: =(C87*T$2)/12 -> 529.48246 | E87: =F87-D87 -> 821.51754 | F87: =IF(C87=0,0,1351) -> 1351 | I87: 650 | N87: =I87-D87 -> 120.51754
B88: 48305 | C88: =C87-E87 -> 181758.64 | D88: =(C88*T$2)/12 -> 527.10006 | E88: =F88-D88 -> 823.89994 | F88: =IF(C88=0,0,1351) -> 1351 | I88: 650 | N88: =I88-D88 -> 122.89994
B89: 48335 | C89: =C88-E88 -> 180934.74 | D89: =(C89*T$2)/12 -> 524.71075 | E89: =F89-D89 -> 826.28925 | F89: =IF(C89=0,0,1351) -> 1351 | I89: 650 | N89: =I89-D89 -> 125.28925
B90: 48366 | C90: =C89-E89 -> 180108.45 | D90: =(C90*T$2)/12 -> 522.31451 | E90: =F90-D90 -> 828.68549 | F90: =IF(C90=0,0,1351) -> 1351 | I90: 650 | N90: =I90-D90 -> 127.68549
B91: 48396 | C91: =C90-E90 -> 179279.77 | D91: =(C91*T$2)/12 -> 519.91132 | E91: =F91-D91 -> 831.08868 | F91: =IF(C91=0,0,1351) -> 1351 | I91: 650 | N91: =I91-D91 -> 130.08868
B92: 48427 | C92: =C91-E91 -> 178448.68 | D92: =(C92*T$2)/12 -> 517.50116 | E92: =F92-D92 -> 833.49884 | F92: =IF(C92=0,0,1351) -> 1351 | I92: 650 | N92: =I92-D92 -> 132.49884
B93: 48457 | C93: =C92-E92 -> 177615.18 | D93: 0 | E93: 0 | F93: 0 | G93: ='Haushalt (Cash)'!$G$28 -> 10000 | N93: =D93-G93 -> -10000
B94: 48458 | C94: =MAX(0,C93-G93) -> 167615.18 | D94: =(C94*T$2)/12 -> 486.08402 | E94: =F94-D94 -> 864.91598 | F94: =IF(C94=0,0,1351) -> 1351 | I94: 650 | N94: =I94-D94 -> 163.91598
B95: 48488 | C95: =C94-E94 -> 166750.26 | D95: =(C95*T$2)/12 -> 483.57576 | E95: =F95-D95 -> 867.42424 | F95: =IF(C95=0,0,1351) -> 1351 | I95: 650 | N95: =I95-D95 -> 166.42424
B96: 48519 | C96: =C95-E95 -> 165882.84 | D96: =(C96*T$2)/12 -> 481.06023 | E96: =F96-D96 -> 869.93977 | F96: =IF(C96=0,0,1351) -> 1351 | I96: 650 | N96: =I96-D96 -> 168.93977
A97: 7 | B97: 48549 | C97: =MAX(0,C96-E96) -> 165012.9 | D97: =(C97*T$2)/12 -> 478.53741 | E97: =F97-D97 -> 872.46259 | F97: =IF(C97=0,0,1351) -> 1351 | I97: 650 | J97: =SUM(E85:E97)+G93 -> 20075.638 | K97: =SUM(I85:I97)-SUM(D85:D97) -> 1663.6377 | L97: 230 | M97: 2500 | N97: =I97-D97 -> 171.46259 | O97: =SUM(N85:N97)+L97+M97 -> -5606.3623 | P97: =K97+L97+M97 -> 4393.6377 | Q97: =P97/J97 -> 0.2188542 | R97: =(C$222 +R19+R32 +R45 +R58+R71+ R84) * W$2 -> 7212.0989 | S97: =P97+R97 -> 11605.737
B98: 48580 | C98: =MAX(0,C97-E97) -> 164140.44 | D98: =(C98*T$2)/12 -> 476.00726 | E98: =F98-D98 -> 874.99274 | F98: =IF(C98=0,0,1351) -> 1351 | I98: 650 | N98: =I98-D98 -> 173.99274
B99: 48611 | C99: =MAX(0,C98-E98) -> 163265.44 | D99: =(C99*T$2)/12 -> 473.46979 | E99: =F99-D99 -> 877.53021 | F99: =IF(C99=0,0,1351) -> 1351 | I99: 650 | N99: =I99-D99 -> 176.53021
B100: 48639 | C100: =MAX(0,C99-E99) -> 162387.91 | D100: =(C100*T$2)/12 -> 470.92495 | E100: =F100-D100 -> 880.07505 | F100: =IF(C100=0,0,1351) -> 1351 | I100: 650 | N100: =I100-D100 -> 179.07505
...

Sheet Alternativszenario 1
A1: Jahr | B1: Datum | C1: Restschuld | D1: Zins | E1: Tilgung | F1: Rate | G1: Sonderzahlung | H1: Sonderkosten | I1: Mieteinnahmen | J1: Preis / qm | K1: Tilgung [Jahr] | L1: Netto Zins Überschuss [Jahr] | M1: Abschreibung Küche | N1: Steuerersparnis Wohnung [netto] | O1: Casflow [mtl] | P1: Casflow [Jahr] | Q1: netto Vermögens-steigerung [Jahr] | R1: ROI dyn | S1: Zinssatz | T1: effektive Steuerlast | U1: EK | V1: Wertsteigerung
J2: 80 | S2: 0.0348 | T2: 0.3 | U2: 92000 | V2: 0.018
B3: 45901 | G3: =U2-H3 -> 74338.8 | H3: 17661.2 | O3: =-H3 -> -17661.2
B4: 45931 | D4: 548.58 | E4: 0 | F4: 548.58 | O4: -548.58
B5: 45962 | D5: 623.5 | E5: 0 | F5: 623.5 | O5: -623.5
B6: 45992 | D6: 623.5 | E6: 0 | F6: 623.5 | K6: =U2-H3 -> 74338.8 | L6: =0-SUM(D3:D6) -> -1795.58 | N6: 533 | O6: -623.5 | P6: =SUM(O3:O6)+N6 -> -18923.78 | Q6: =L6+N6-H3 -> -18923.78 | R6: =Q6/K6 -> -0.25456128
B7: 46023 | D7: 623.5 | E7: 0 | F7: 623.5 | H7: 4000 | O7: -4623.5
B8: 46054 | D8: 700 | E8: 0 | F8: 700 | O8: -623.5
B9: 46082 | D9: 750 | E9: 0 | F9: 750 | O9: -623.5
B10: 46113 | C10: 288000 | D10: =(C10*S2)/12 -> 835.2 | E10: =F10-D10 -> 515.8 | F10: 1351 | I10: 700 | O10: =I10-D10 -> -135.2
B11: 46143 | C11: =C10-E10 -> 287484.2 | D11: =(C11*S$2)/12 -> 833.70418 | E11: =F11-D11 -> 517.29582 | F11: 1351 | I11: 700 | O11: =I11-D11 -> -133.70418
B12: 46174 | C12: =C11-E11 -> 286966.9 | D12: =(C12*S$2)/12 -> 832.20402 | E12: =F12-D12 -> 518.79598 | F12: 1351 | I12: 700 | O12: =I12-D12 -> -132.20402
B13: 46204 | C13: =C12-E12 -> 286448.11 | D13: =(C13*S$2)/12 -> 830.69951 | E13: =F13-D13 -> 520.30049 | F13: 1351 | I13: 700 | O13: =I13-D13 -> -130.69951
B14: 46235 | C14: =C13-E13 -> 285927.81 | D14: =(C14*S$2)/12 -> 829.19064 | E14: =F14-D14 -> 521.80936 | F14: 1351 | I14: 700 | O14: =I14-D14 -> -129.19064
B15: 46265 | C15: =C14-E14 -> 285406 | D15: 0 | E15: 0 | F15: 0 | O15: =D15-G15 -> 0
B16: 46266 | C16: =C15-G15 -> 285406 | D16: =(C16*S$2)/12 -> 827.6774 | E16: =F16-D16 -> 523.3226 | F16: 1351 | I16: 700 | O16: =I16-D16 -> -127.6774
B17: 46296 | C17: =C16-E16 -> 284882.68 | D17: =(C17*S$2)/12 -> 826.15976 | E17: =F17-D17 -> 524.84024 | F17: 1351 | I17: 700 | O17: =I17-D17 -> -126.15976
B18: 46327 | C18: =C17-E17 -> 284357.84 | D18: =(C18*S$2)/12 -> 824.63772 | E18: =F18-D18 -> 526.36228 | F18: 1351 | I18: 700 | O18: =I18-D18 -> -124.63772
A19: 1 | B19: 46357 | C19: =C18-E18 -> 283831.47 | D19: =(C19*S$2)/12 -> 823.11127 | E19: =F19-D19 -> 527.88873 | F19: 1351 | I19: 700 | J19: =(I19/$J$2)/0.66 -> 13.257576 | K19: =SUM(E7:E19)+G15 -> 4696.4155 | L19: =SUM(I7:I19)-SUM(D7:D19) -> -3236.0845 | M19: 230 | N19: 3040 | O19: =I19-D19 -> -123.11127 | P19: =SUM(O7:O19)+M19+N19 -> -3763.0845 | Q19: =L19+M19+N19-H7 -> -3966.0845 | R19: =Q19/K19 -> -0.84449183
B20: 46388 | C20: =C19-E19 -> 283303.58 | D20: =(C20*S$2)/12 -> 821.5804 | E20: =F20-D20 -> 529.4196 | F20: 1351 | I20: 700 | O20: =I20-D20 -> -121.5804
B21: 46419 | C21: =C20-E20 -> 282774.16 | D21: =(C21*S$2)/12 -> 820.04508 | E21: =F21-D21 -> 530.95492 | F21: 1351 | I21: 700 | O21: =I21-D21 -> -120.04508
B22: 46447 | C22: =C21-E21 -> 282243.21 | D22: =(C22*S$2)/12 -> 818.50531 | E22: =F22-D22 -> 532.49469 | F22: 1351 | I22: 700 | O22: =I22-D22 -> -118.50531
B23: 46478 | C23: =C22-E22 -> 281710.72 | D23: =(C23*S$2)/12 -> 816.96107 | E23: =F23-D23 -> 534.03893 | F23: 1351 | I23: 700 | O23: =I23-D23 -> -116.96107
B24: 46508 | C24: =C23-E23 -> 281176.68 | D24: =(C24*S$2)/12 -> 815.41236 | E24: =F24-D24 -> 535.58764 | F24: 1351 | I24: 700 | O24: =I24-D24 -> -115.41236
B25: 46539 | C25: =C24-E24 -> 280641.09 | D25: =(C25*S$2)/12 -> 813.85916 | E25: =F25-D25 -> 537.14084 | F25: 1351 | I25: 700 | O25: =I25-D25 -> -113.85916
B26: 46569 | C26: =C25-E25 -> 280103.95 | D26: =(C26*S$2)/12 -> 812.30145 | E26: =F26-D26 -> 538.69855 | F26: 1351 | I26: 700 | O26: =I26-D26 -> -112.30145
B27: 46600 | C27: =C26-E26 -> 279565.25 | D27: =(C27*S$2)/12 -> 810.73922 | E27: =F27-D27 -> 540.26078 | F27: 1351 | I27: 700 | O27: =I27-D27 -> -110.73922
B28: 46630 | C28: =C27-E27 -> 279024.99 | D28: 0 | E28: 0 | F28: 0 | O28: =D28-G28 -> 0
B29: 46631 | C29: =C28-G28 -> 279024.99 | D29: =(C29*S$2)/12 -> 809.17247 | E29: =F29-D29 -> 541.82753 | F29: 1351 | I29: 700 | O29: =I29-D29 -> -109.17247
B30: 46661 | C30: =C29-E29 -> 278483.16 | D30: =(C30*S$2)/12 -> 807.60117 | E30: =F30-D30 -> 543.39883 | F30: 1351 | I30: 700 | O30: =I30-D30 -> -107.60117
A31: 1.015 | B31: 46692 | C31: =C30-E30 -> 277939.76 | D31: =(C31*S$2)/12 -> 806.02531 | E31: =F31-D31 -> 544.97469 | F31: 1351 | I31: 700 | O31: =I31-D31 -> -106.02531
A32: 2 | B32: 46722 | C32: =C31-E31 -> 277394.79 | D32: =(C32*S$2)/12 -> 804.44488 | E32: =F32-D32 -> 546.55512 | F32: 1351 | I32: =I31*A31 -> 710.5 | J32: =(I32/$J$2)/0.66 -> 13.456439 | K32: =SUM(E20:E32)+G28 -> 6455.3521 | L32: =SUM(I20:I32)-SUM(D20:D32) -> -1346.1479 | M32: 230 | N32: 2500 | O32: =I32-D32 -> -93.944884 | P32: =SUM(O20:O32)+M32+N32 -> 1383.8521 | Q32: =L32+M32+N32 -> 1383.8521 | R32: =Q32/K32 -> 0.21437283
B33: 46753 | C33: =C32-E32 -> 276848.23 | D33: =(C33*S$2)/12 -> 802.85987 | E33: =F33-D33 -> 548.14013 | F33: 1351 | I33: =I32 -> 710.5 | O33: =I33-D33 -> -92.359874
B34: 46784 | C34: =C33-E33 -> 276300.09 | D34: =(C34*S$2)/12 -> 801.27027 | E34: =F34-D34 -> 549.72973 | F34: 1351 | I34: =I33 -> 710.5 | O34: =I34-D34 -> -90.770268
B35: 46813 | C35: =C34-E34 -> 275750.36 | D35: =(C35*S$2)/12 -> 799.67605 | E35: =F35-D35 -> 551.32395 | F35: 1351 | I35: =I34 -> 710.5 | O35: =I35-D35 -> -89.176051
B36: 46844 | C36: =C35-E35 -> 275199.04 | D36: =(C36*S$2)/12 -> 798.07721 | E36: =F36-D36 -> 552.92279 | F36: 1351 | I36: =I35 -> 710.5 | O36: =I36-D36 -> -87.577212
B37: 46874 | C37: =C36-E36 -> 274646.12 | D37: =(C37*S$2)/12 -> 796.47374 | E37: =F37-D37 -> 554.52626 | F37: 1351 | I37: =I36 -> 710.5 | O37: =I37-D37 -> -85.973736
B38: 46905 | C38: =C37-E37 -> 274091.59 | D38: =(C38*S$2)/12 -> 794.86561 | E38: =F38-D38 -> 556.13439 | F38: 1351 | I38: =I37 -> 710.5 | O38: =I38-D38 -> -84.36561
B39: 46935 | C39: =C38-E38 -> 273535.46 | D39: =(C39*S$2)/12 -> 793.25282 | E39: =F39-D39 -> 557.74718 | F39: 1351 | I39: =I38 -> 710.5 | O39: =I39-D39 -> -82.75282
B40: 46966 | C40: =C39-E39 -> 272977.71 | D40: =(C40*S$2)/12 -> 791.63535 | E40: =F40-D40 -> 559.36465 | F40: 1351 | I40: =I39 -> 710.5 | O40: =I40-D40 -> -81.135353
B41: 46996 | C41: =C40-E40 -> 272418.34 | D41: 0 | E41: 0 | F41: 0 | O41: =D41-G41 -> 0
B42: 46997 | C42: =C41-G41 -> 272418.34 | D42: =(C42*S$2)/12 -> 790.0132 | E42: =F42-D42 -> 560.9868 | F42: 1351 | I42: =I40 -> 710.5 | O42: =I42-D42 -> -79.513196
B43: 47027 | C43: =C42-E42 -> 271857.36 | D43: =(C43*S$2)/12 -> 788.38633 | E43: =F43-D43 -> 562.61367 | F43: 1351 | I43: =I42 -> 710.5 | O43: =I43-D43 -> -77.886334
B44: 47058 | C44: =C43-E43 -> 271294.74 | D44: =(C44*S$2)/12 -> 786.75475 | E44: =F44-D44 -> 564.24525 | F44: 1351 | I44: =I43 -> 710.5 | O44: =I44-D44 -> -76.254754
A45: 3 | B45: 47088 | C45: =C44-E44 -> 270730.5 | D45: =(C45*S$2)/12 -> 785.11844 | E45: =F45-D45 -> 565.88156 | F45: 1351 | I45: =I44*$A31 -> 721.1575 | J45: =(I45/$J$2)/0.66 -> 13.658286 | K45: =SUM(E33:E45)+G41 -> 6683.6164 | L45: =SUM(I33:I45)-SUM(D33:D45) -> -991.72615 | M45: 230 | N45: 2500 | O45: =I45-D45 -> -63.960943 | P45: =SUM(O33:O45)+M45+N45 -> 1738.2739 | Q45: =L45+M45+N45 -> 1738.2739 | R45: =Q45/K45 -> 0.26007984
B46: 47119 | C46: =C45-E45 -> 270164.62 | D46: =(C46*S$2)/12 -> 783.47739 | E46: =F46-D46 -> 567.52261 | F46: 1351 | I46: =I45 -> 721.1575 | O46: =I46-D46 -> -62.319886
B47: 47150 | C47: =C46-E46 -> 269597.09 | D47: =(C47*S$2)/12 -> 781.83157 | E47: =F47-D47 -> 569.16843 | F47: 1351 | I47: =I46 -> 721.1575 | O47: =I47-D47 -> -60.674071
B48: 47178 | C48: =C47-E47 -> 269027.92 | D48: =(C48*S$2)/12 -> 780.18098 | E48: =F48-D48 -> 570.81902 | F48: 1351 | I48: =I47 -> 721.1575 | O48: =I48-D48 -> -59.023482
B49: 47209 | C49: =C48-E48 -> 268457.11 | D49: =(C49*S$2)/12 -> 778.52561 | E49: =F49-D49 -> 572.47439 | F49: 1351 | I49: =I48 -> 721.1575 | O49: =I49-D49 -> -57.368107
B50: 47239 | C50: =C49-E49 -> 267884.63 | D50: =(C50*S$2)/12 -> 776.86543 | E50: =F50-D50 -> 574.13457 | F50: 1351 | I50: =I49 -> 721.1575 | O50: =I50-D50 -> -55.707932
B51: 47270 | C51: =C50-E50 -> 267310.5 | D51: =(C51*S$2)/12 -> 775.20044 | E51: =F51-D51 -> 575.79956 | F51: 1351 | I51: =I50 -> 721.1575 | O51: =I51-D51 -> -54.042941
B52: 47300 | C52: =C51-E51 -> 266734.7 | D52: =(C52*S$2)/12 -> 773.53062 | E52: =F52-D52 -> 577.46938 | F52: 1351 | I52: =I51 -> 721.1575 | O52: =I52-D52 -> -52.373123
B53: 47331 | C53: =C52-E52 -> 266157.23 | D53: =(C53*S$2)/12 -> 771.85596 | E53: =F53-D53 -> 579.14404 | F53: 1351 | I53: =I52 -> 721.1575 | O53: =I53-D53 -> -50.698461
B54: 47361 | C54: =C53-E53 -> 265578.08 | D54: 0 | E54: 0 | F54: 0 | O54: =D54-G54 -> 0
B55: 47362 | C55: =C54-G54 -> 265578.08 | D55: =(C55*S$2)/12 -> 770.17644 | E55: =F55-D55 -> 580.82356 | F55: 1351 | I55: =I53 -> 721.1575 | O55: =I55-D55 -> -49.018944
B56: 47392 | C56: =C55-E55 -> 264997.26 | D56: =(C56*S$2)/12 -> 768.49206 | E56: =F56-D56 -> 582.50794 | F56: 1351 | I56: =I55 -> 721.1575 | O56: =I56-D56 -> -47.334555
B57: 47423 | C57: =C56-E56 -> 264414.75 | D57: =(C57*S$2)/12 -> 766.80278 | E57: =F57-D57 -> 584.19722 | F57: 1351 | I57: =I55 -> 721.1575 | O57: =I57-D57 -> -45.645282
A58: 4 | B58: 47453 | C58: =C57-E57 -> 263830.56 | D58: =(C58*S$2)/12 -> 765.10861 | E58: =F58-D58 -> 585.89139 | F58: 1351 | I58: =I57*$A$31 -> 731.97486 | J58: =(I58/$J$2)/0.66 -> 13.86316 | K58: =SUM(E46:E58)+G54 -> 6919.9521 | L58: =SUM(I46:I58)-SUM(D46:D58) -> -627.34053 | M58: 230 | N58: 2500 | O58: =I58-D58 -> -33.133748 | P58: =SUM(O46:O58)+M58+N58 -> 2102.6595 | Q58: =L58+M58+N58 -> 2102.6595 | R58: =Q58/K58 -> 0.30385463
B59: 47484 | C59: =C58-E58 -> 263244.66 | D59: =(C59*S$2)/12 -> 763.40953 | E59: =F59-D59 -> 587.59047 | F59: 1351 | I59: =I58 -> 731.97486 | O59: =I59-D59 -> -31.434663
B60: 47515 | C60: =C59-E59 -> 262657.07 | D60: =(C60*S$2)/12 -> 761.70551 | E60: =F60-D60 -> 589.29449 | F60: 1351 | I60: =I59 -> 731.97486 | O60: =I60-D60 -> -29.730651
B61: 47543 | C61: =C60-E60 -> 262067.78 | D61: =(C61*S$2)/12 -> 759.99656 | E61: =F61-D61 -> 591.00344 | F61: 1351 | I61: =I60 -> 731.97486 | O61: =I61-D61 -> -28.021697
B62: 47574 | C62: =C61-E61 -> 261476.78 | D62: =(C62*S$2)/12 -> 758.28265 | E62: =F62-D62 -> 592.71735 | F62: 1351 | I62: =I61 -> 731.97486 | O62: =I62-D62 -> -26.307787
B63: 47604 | C63: =C62-E62 -> 260884.06 | D63: =(C63*S$2)/12 -> 756.56377 | E63: =F63-D63 -> 594.43623 | F63: 1351 | I63: =I62 -> 731.97486 | O63: =I63-D63 -> -24.588906
B64: 47635 | C64: =C63-E63 -> 260289.62 | D64: =(C64*S$2)/12 -> 754.8399 | E64: =F64-D64 -> 596.1601 | F64: 1351 | I64: =I63 -> 731.97486 | O64: =I64-D64 -> -22.865041
B65: 47665 | C65: =C64-E64 -> 259693.46 | D65: =(C65*S$2)/12 -> 753.11104 | E65: =F65-D65 -> 597.88896 | F65: 1351 | I65: =I64 -> 731.97486 | O65: =I65-D65 -> -21.136177
B66: 47696 | C66: =C65-E65 -> 259095.57 | D66: =(C66*S$2)/12 -> 751.37716 | E66: =F66-D66 -> 599.62284 | F66: 1351 | I66: =I65 -> 731.97486 | O66: =I66-D66 -> -19.402299
B67: 47726 | C67: =C66-E66 -> 258495.95 | D67: 0 | E67: 0 | F67: 0 | O67: =D67-G67 -> 0
B68: 47727 | C68: =C67-G67 -> 258495.95 | D68: =(C68*S$2)/12 -> 749.63826 | E68: =F68-D68 -> 601.36174 | F68: 1351 | I68: =I66 -> 731.97486 | O68: =I68-D68 -> -17.663393
B69: 47757 | C69: =C68-E68 -> 257894.59 | D69: =(C69*S$2)/12 -> 747.89431 | E69: =F69-D69 -> 603.10569 | F69: 1351 | I69: =I68 -> 731.97486 | O69: =I69-D69 -> -15.919444
B70: 47788 | C70: =C69-E69 -> 257291.48 | D70: =(C70*S$2)/12 -> 746.1453 | E70: =F70-D70 -> 604.8547 | F70: 1351 | I70: =I68 -> 731.97486 | O70: =I70-D70 -> -14.170437
A71: 5 | B71: 47818 | C71: =C70-E70 -> 256686.63 | D71: =(C71*S$2)/12 -> 744.39122 | E71: =F71-D71 -> 606.60878 | F71: 1351 | I71: =I70*$A$31 -> 742.95449 | J71: =(I71/$J$2)/0.66 -> 14.071108 | K71: =SUM(E59:E71)+G67 -> 7164.6448 | L71: =SUM(I59:I71)-SUM(D59:D71) -> -252.67723 | M71: 230 | N71: 2500 | O71: =I71-D71 -> -1.4367355 | P71: =SUM(O59:O71)+M71+N71 -> 2477.3228 | Q71: =L71+M71+N71 -> 2477.3228 | R71: =Q71/K71 -> 0.34577049
B72: 47849 | C72: =C71-E71 -> 256080.02 | D72: =(C72*S$2)/12 -> 742.63206 | E72: =F72-D72 -> 608.36794 | F72: 1351 | I72: =I71 -> 742.95449 | O72: =I72-D72 -> 0.32242996
B73: 47880 | C73: =C72-E72 -> 255471.65 | D73: =(C73*S$2)/12 -> 740.86779 | E73: =F73-D73 -> 610.13221 | F73: 1351 | I73: =I72 -> 742.95449 | O73: =I73-D73 -> 2.086697
B74: 47908 | C74: =C73-E73 -> 254861.52 | D74: =(C74*S$2)/12 -> 739.09841 | E74: =F74-D74 -> 611.90159 | F74: 1351 | I74: =I73 -> 742.95449 | O74: =I74-D74 -> 3.8560804
B75: 47939 | C75: =C74-E74 -> 254249.62 | D75: =(C75*S$2)/12 -> 737.32389 | E75: =F75-D75 -> 613.67611 | F75: 1351 | I75: =I74 -> 742.95449 | O75: =I75-D75 -> 5.630595
B76: 47969 | C76: =C75-E75 -> 253635.94 | D76: =(C76*S$2)/12 -> 735.54423 | E76: =F76-D76 -> 615.45577 | F76: 1351 | I76: =I75 -> 742.95449 | O76: =I76-D76 -> 7.4102558
B77: 48000 | C77: =C76-E76 -> 253020.49 | D77: =(C77*S$2)/12 -> 733.75941 | E77: =F77-D77 -> 617.24059 | F77: 1351 | I77: =I76 -> 742.95449 | O77: =I77-D77 -> 9.1950775
B78: 48030 | C78: =C77-E77 -> 252403.24 | D78: =(C78*S$2)/12 -> 731.96941 | E78: =F78-D78 -> 619.03059 | F78: 1351 | I78: =I77 -> 742.95449 | O78: =I78-D78 -> 10.985075
B79: 48061 | C79: =C78-E78 -> 251784.21 | D79: =(C79*S$2)/12 -> 730.17422 | E79: =F79-D79 -> 620.82578 | F79: 1351 | I79: =I78 -> 742.95449 | O79: =I79-D79 -> 12.780264
B80: 48091 | C80: =C79-E79 -> 251163.39 | D80: 0 | E80: 0 | F80: 0 | O80: =D80-G80 -> 0
B81: 48092 | C81: =C80-G80 -> 251163.39 | D81: =(C81*S$2)/12 -> 728.37383 | E81: =F81-D81 -> 622.62617 | F81: 1351 | I81: =I79 -> 742.95449 | O81: =I81-D81 -> 14.580659
B82: 48122 | C82: =C81-E81 -> 250540.76 | D82: =(C82*S$2)/12 -> 726.56821 | E82: =F82-D82 -> 624.43179 | F82: 1351 | I82: =I81 -> 742.95449 | O82: =I82-D82 -> 16.386275
B83: 48153 | C83: =C82-E82 -> 249916.33 | D83: =(C83*S$2)/12 -> 724.75736 | E83: =F83-D83 -> 626.24264 | F83: 1351 | I83: =I81 -> 742.95449 | O83: =I83-D83 -> 18.197127
A84: 6 | B84: 48183 | C84: =C83-E83 -> 249290.09 | D84: =(C84*S$2)/12 -> 722.94126 | E84: =F84-D84 -> 628.05874 | F84: 1351 | I84: =I83*$A$31 -> 754.0988 | J84: =(I84/$J$2)/0.66 -> 14.282174 | K84: =SUM(E72:E84)+G80 -> 7417.9899 | L84: =SUM(I72:I84)-SUM(D72:D84) -> 132.58808 | M84: 230 | N84: 2500 | O84: =I84-D84 -> 31.157548 | P84: =SUM(O72:O84)+M84+N84 -> 2862.5881 | Q84: =L84+M84+N84 -> 2862.5881 | R84: =Q84/K84 -> 0.38589808
B85: 48214 | C85: =C84-E84 -> 248662.03 | D85: =(C85*S$2)/12 -> 721.11988 | E85: =F85-D85 -> 629.88012 | F85: 1351 | I85: =I84 -> 754.0988 | O85: =I85-D85 -> 32.978918
B86: 48245 | C86: =C85-E85 -> 248032.15 | D86: =(C86*S$2)/12 -> 719.29323 | E86: =F86-D86 -> 631.70677 | F86: 1351 | I86: =I85 -> 754.0988 | O86: =I86-D86 -> 34.80557
B87: 48274 | C87: =C86-E86 -> 247400.44 | D87: =(C87*S$2)/12 -> 717.46128 | E87: =F87-D87 -> 633.53872 | F87: 1351 | I87: =I86 -> 754.0988 | O87: =I87-D87 -> 36.63752
B88: 48305 | C88: =C87-E87 -> 246766.9 | D88: =(C88*S$2)/12 -> 715.62402 | E88: =F88-D88 -> 635.37598 | F88: 1351 | I88: =I87 -> 754.0988 | O88: =I88-D88 -> 38.474782
B89: 48335 | C89: =C88-E88 -> 246131.53 | D89: =(C89*S$2)/12 -> 713.78143 | E89: =F89-D89 -> 637.21857 | F89: 1351 | I89: =I88 -> 754.0988 | O89: =I89-D89 -> 40.317373
B90: 48366 | C90: =C89-E89 -> 245494.31 | D90: =(C90*S$2)/12 -> 711.9335 | E90: =F90-D90 -> 639.0665 | F90: 1351 | I90: =I89 -> 754.0988 | O90: =I90-D90 -> 42.165307
B91: 48396 | C91: =C90-E90 -> 244855.24 | D91: =(C91*S$2)/12 -> 710.0802 | E91: =F91-D91 -> 640.9198 | F91: 1351 | I91: =I90 -> 754.0988 | O91: =I91-D91 -> 44.018599
B92: 48427 | C92: =C91-E91 -> 244214.32 | D92: =(C92*S$2)/12 -> 708.22154 | E92: =F92-D92 -> 642.77846 | F92: 1351 | I92: =I91 -> 754.0988 | O92: =I92-D92 -> 45.877267
B93: 48457 | C93: =C92-E92 -> 243571.54 | D93: 0 | E93: 0 | F93: 0 | O93: =D93-G93 -> 0
B94: 48458 | C94: =C93-G93 -> 243571.54 | D94: =(C94*S$2)/12 -> 706.35748 | E94: =F94-D94 -> 644.64252 | F94: 1351 | I94: =I92 -> 754.0988 | O94: =I94-D94 -> 47.741324
B95: 48488 | C95: =C94-E94 -> 242926.9 | D95: =(C95*S$2)/12 -> 704.48802 | E95: =F95-D95 -> 646.51198 | F95: 1351 | I95: =I94 -> 754.0988 | O95: =I95-D95 -> 49.610788
B96: 48519 | C96: =C95-E95 -> 242280.39 | D96: =(C96*S$2)/12 -> 702.61313 | E96: =F96-D96 -> 648.38687 | F96: 1351 | I96: =I94 -> 754.0988 | O96: =I96-D96 -> 51.485672
A97: 7 | B97: 48549 | C97: =C96-E96 -> 241632 | D97: =(C97*S$2)/12 -> 700.73281 | E97: =F97-D97 -> 650.26719 | F97: 1351 | I97: =I96*$A$31 -> 765.41028 | J97: =(I97/$J$2)/0.66 -> 14.496407 | K97: =SUM(E85:E97)+G93 -> 7680.2935 | L97: =SUM(I85:I97)-SUM(D85:D97) -> 528.7906 | M97: 230 | N97: 2500 | O97: =I97-D97 -> 64.677476 | P97: =SUM(O85:O97)+M97+N97 -> 3258.7906 | Q97: =L97+M97+N97 -> 3258.7906 | R97: =Q97/K97 -> 0.42430548
B98: 48580 | C98: =C97-E97 -> 240981.74 | D98: =(C98*S$2)/12 -> 698.84703 | E98: =F98-D98 -> 652.15297 | F98: 1351 | I98: =I97 -> 765.41028 | O98: =I98-D98 -> 66.563251
B99: 48611 | C99: =C98-E98 -> 240329.58 | D99: =(C99*S$2)/12 -> 696.95579 | E99: =F99-D99 -> 654.04421 | F99: 1351 | I99: =I98 -> 765.41028 | O99: =I99-D99 -> 68.454495
B100: 48639 | C100: =C99-E99 -> 239675.54 | D100: =(C100*S$2)/12 -> 695.05906 | E100: =F100-D100 -> 655.94094 | F100: 1351 | I100: =I99 -> 765.41028 | O100: =I100-D100 -> 70.351223
...

Sheet Alternativszenario 2
A1: Jahr | B1: Datum | C1: Restschuld | D1: Zins | E1: Tilgung | F1: Rate | G1: Sonderzahlung | H1: Sonderkosten | I1: Mieteinnahmen | J1: Preis / qm | K1: Tilgung [Jahr] | L1: Netto Zins Überschuss [Jahr] | M1: Abschreibung Küche | N1: Steuerersparnis Wohnung [netto] | O1: Casflow [mtl] | P1: Casflow [Jahr] | Q1: netto Vermögens-steigerung [Jahr] | R1: ROI dyn | S1: Zinssatz | T1: effektive Steuerlast | U1: EK | V1: Wertsteigerung
J2: 80 | S2: 0.0348 | T2: 0.3 | U2: 92000 | V2: 0.018
B3: 45901 | G3: =U2-H3 -> 74338.8 | H3: 17661.2 | O3: =-H3 -> -17661.2
B4: 45931 | D4: 548.58 | E4: 0 | F4: 548.58 | O4: -548.58
B5: 45962 | D5: 623.5 | E5: 0 | F5: 623.5 | O5: -623.5
B6: 45992 | D6: 623.5 | E6: 0 | F6: 623.5 | K6: =U2-H3 -> 74338.8 | L6: =0-SUM(D3:D6) -> -1795.58 | N6: 533 | O6: -623.5 | P6: =SUM(O3:O6)+N6 -> -18923.78 | Q6: =L6+N6-H3 -> -18923.78 | R6: =Q6/K6 -> -0.25456128
B7: 46023 | D7: 623.5 | E7: 0 | F7: 623.5 | H7: 4000 | O7: -4623.5
B8: 46054 | D8: 700 | E8: 0 | F8: 700 | O8: -623.5
B9: 46082 | D9: 750 | E9: 0 | F9: 750 | O9: -623.5
B10: 46113 | C10: 288000 | D10: =(C10*S2)/12 -> 835.2 | E10: =F10-D10 -> 515.8 | F10: 1351 | I10: 700 | O10: =I10-D10 -> -135.2
B11: 46143 | C11: =C10-E10 -> 287484.2 | D11: =(C11*S$2)/12 -> 833.70418 | E11: =F11-D11 -> 517.29582 | F11: 1351 | I11: 700 | O11: =I11-D11 -> -133.70418
B12: 46174 | C12: =C11-E11 -> 286966.9 | D12: =(C12*S$2)/12 -> 832.20402 | E12: =F12-D12 -> 518.79598 | F12: 1351 | I12: 700 | O12: =I12-D12 -> -132.20402
B13: 46204 | C13: =C12-E12 -> 286448.11 | D13: =(C13*S$2)/12 -> 830.69951 | E13: =F13-D13 -> 520.30049 | F13: 1351 | I13: 700 | O13: =I13-D13 -> -130.69951
B14: 46235 | C14: =C13-E13 -> 285927.81 | D14: =(C14*S$2)/12 -> 829.19064 | E14: =F14-D14 -> 521.80936 | F14: 1351 | I14: 700 | O14: =I14-D14 -> -129.19064
B15: 46265 | C15: =C14-E14 -> 285406 | D15: 0 | E15: 0 | F15: 0 | O15: =D15-G15 -> 0
B16: 46266 | C16: =C15-G15 -> 285406 | D16: =(C16*S$2)/12 -> 827.6774 | E16: =F16-D16 -> 523.3226 | F16: 1351 | I16: 700 | O16: =I16-D16 -> -127.6774
B17: 46296 | C17: =C16-E16 -> 284882.68 | D17: =(C17*S$2)/12 -> 826.15976 | E17: =F17-D17 -> 524.84024 | F17: 1351 | I17: 700 | O17: =I17-D17 -> -126.15976
B18: 46327 | C18: =C17-E17 -> 284357.84 | D18: =(C18*S$2)/12 -> 824.63772 | E18: =F18-D18 -> 526.36228 | F18: 1351 | I18: 700 | O18: =I18-D18 -> -124.63772
A19: 1 | B19: 46357 | C19: =C18-E18 -> 283831.47 | D19: =(C19*S$2)/12 -> 823.11127 | E19: =F19-D19 -> 527.88873 | F19: 1351 | I19: 700 | J19: =(I19/$J$2)/0.66 -> 13.257576 | K19: =SUM(E7:E19)+G15 -> 4696.4155 | L19: =SUM(I7:I19)-SUM(D7:D19) -> -3236.0845 | M19: 230 | N19: 3040 | O19: =I19-D19 -> -123.11127 | P19: =SUM(O7:O19)+M19+N19 -> -3763.0845 | Q19: =L19+M19+N19-H7 -> -3966.0845 | R19: =Q19/K19 -> -0.84449183
B20: 46388 | C20: =C19-E19 -> 283303.58 | D20: =(C20*S$2)/12 -> 821.5804 | E20: =F20-D20 -> 529.4196 | F20: 1351 | I20: 700 | O20: =I20-D20 -> -121.5804
B21: 46419 | C21: =C20-E20 -> 282774.16 | D21: =(C21*S$2)/12 -> 820.04508 | E21: =F21-D21 -> 530.95492 | F21: 1351 | I21: 700 | O21: =I21-D21 -> -120.04508
B22: 46447 | C22: =C21-E21 -> 282243.21 | D22: =(C22*S$2)/12 -> 818.50531 | E22: =F22-D22 -> 532.49469 | F22: 1351 | I22: 700 | O22: =I22-D22 -> -118.50531
B23: 46478 | C23: =C22-E22 -> 281710.72 | D23: =(C23*S$2)/12 -> 816.96107 | E23: =F23-D23 -> 534.03893 | F23: 1351 | I23: 700 | O23: =I23-D23 -> -116.96107
B24: 46508 | C24: =C23-E23 -> 281176.68 | D24: =(C24*S$2)/12 -> 815.41236 | E24: =F24-D24 -> 535.58764 | F24: 1351 | I24: 700 | O24: =I24-D24 -> -115.41236
B25: 46539 | C25: =C24-E24 -> 280641.09 | D25: =(C25*S$2)/12 -> 813.85916 | E25: =F25-D25 -> 537.14084 | F25: 1351 | I25: 700 | O25: =I25-D25 -> -113.85916
B26: 46569 | C26: =C25-E25 -> 280103.95 | D26: =(C26*S$2)/12 -> 812.30145 | E26: =F26-D26 -> 538.69855 | F26: 1351 | I26: 700 | O26: =I26-D26 -> -112.30145
B27: 46600 | C27: =C26-E26 -> 279565.25 | D27: =(C27*S$2)/12 -> 810.73922 | E27: =F27-D27 -> 540.26078 | F27: 1351 | I27: 700 | O27: =I27-D27 -> -110.73922
B28: 46630 | C28: =C27-E27 -> 279024.99 | D28: 0 | E28: 0 | F28: 0 | O28: =D28-G28 -> 0
B29: 46631 | C29: =C28-G28 -> 279024.99 | D29: =(C29*S$2)/12 -> 809.17247 | E29: =F29-D29 -> 541.82753 | F29: 1351 | I29: 700 | O29: =I29-D29 -> -109.17247
B30: 46661 | C30: =C29-E29 -> 278483.16 | D30: =(C30*S$2)/12 -> 807.60117 | E30: =F30-D30 -> 543.39883 | F30: 1351 | I30: 700 | O30: =I30-D30 -> -107.60117
A31: 1.015 | B31: 46692 | C31: =C30-E30 -> 277939.76 | D31: =(C31*S$2)/12 -> 806.02531 | E31: =F31-D31 -> 544.97469 | F31: 1351 | I31: 700 | O31: =I31-D31 -> -106.02531
A32: 2 | B32: 46722 | C32: =C31-E31 -> 277394.79 | D32: =(C32*S$2)/12 -> 804.44488 | E32: =F32-D32 -> 546.55512 | F32: 1351 | I32: 700 | J32: =(I32/$J$2)/0.66 -> 13.257576 | K32: =SUM(E20:E32)+G28 -> 6455.3521 | L32: =SUM(I20:I32)-SUM(D20:D32) -> -1356.6479 | M32: 230 | N32: 2500 | O32: =I32-D32 -> -104.44488 | P32: =SUM(O20:O32)+M32+N32 -> 1373.3521 | Q32: =L32+M32+N32 -> 1373.3521 | R32: =Q32/K32 -> 0.21274628
B33: 46753 | C33: =C32-E32 -> 276848.23 | D33: =(C33*S$2)/12 -> 802.85987 | E33: =F33-D33 -> 548.14013 | F33: 1351 | I33: =I32 -> 700 | O33: =I33-D33 -> -102.85987
B34: 46784 | C34: =C33-E33 -> 276300.09 | D34: =(C34*S$2)/12 -> 801.27027 | E34: =F34-D34 -> 549.72973 | F34: 1351 | I34: =I33 -> 700 | O34: =I34-D34 -> -101.27027
B35: 46813 | C35: =C34-E34 -> 275750.36 | D35: =(C35*S$2)/12 -> 799.67605 | E35: =F35-D35 -> 551.32395 | F35: 1351 | I35: =I34 -> 700 | O35: =I35-D35 -> -99.676051
B36: 46844 | C36: =C35-E35 -> 275199.04 | D36: =(C36*S$2)/12 -> 798.07721 | E36: =F36-D36 -> 552.92279 | F36: 1351 | I36: =I35 -> 700 | O36: =I36-D36 -> -98.077212
B37: 46874 | C37: =C36-E36 -> 274646.12 | D37: =(C37*S$2)/12 -> 796.47374 | E37: =F37-D37 -> 554.52626 | F37: 1351 | I37: =I36 -> 700 | O37: =I37-D37 -> -96.473736
B38: 46905 | C38: =C37-E37 -> 274091.59 | D38: =(C38*S$2)/12 -> 794.86561 | E38: =F38-D38 -> 556.13439 | F38: 1351 | I38: =I37 -> 700 | O38: =I38-D38 -> -94.86561
B39: 46935 | C39: =C38-E38 -> 273535.46 | D39: =(C39*S$2)/12 -> 793.25282 | E39: =F39-D39 -> 557.74718 | F39: 1351 | I39: =I38 -> 700 | O39: =I39-D39 -> -93.25282
B40: 46966 | C40: =C39-E39 -> 272977.71 | D40: =(C40*S$2)/12 -> 791.63535 | E40: =F40-D40 -> 559.36465 | F40: 1351 | I40: =I39 -> 700 | O40: =I40-D40 -> -91.635353
B41: 46996 | C41: =C40-E40 -> 272418.34 | D41: 0 | E41: 0 | F41: 0 | O41: =D41-G41 -> 0
B42: 46997 | C42: =C41-G41 -> 272418.34 | D42: =(C42*S$2)/12 -> 790.0132 | E42: =F42-D42 -> 560.9868 | F42: 1351 | I42: =I40 -> 700 | O42: =I42-D42 -> -90.013196
B43: 47027 | C43: =C42-E42 -> 271857.36 | D43: =(C43*S$2)/12 -> 788.38633 | E43: =F43-D43 -> 562.61367 | F43: 1351 | I43: =I42 -> 700 | O43: =I43-D43 -> -88.386334
B44: 47058 | C44: =C43-E43 -> 271294.74 | D44: =(C44*S$2)/12 -> 786.75475 | E44: =F44-D44 -> 564.24525 | F44: 1351 | I44: =I43 -> 700 | O44: =I44-D44 -> -86.754754
A45: 3 | B45: 47088 | C45: =C44-E44 -> 270730.5 | D45: =(C45*S$2)/12 -> 785.11844 | E45: =F45-D45 -> 565.88156 | F45: 1351 | I45: 700 | J45: =(I45/$J$2)/0.66 -> 13.257576 | K45: =SUM(E33:E45)+G41 -> 6683.6164 | L45: =SUM(I33:I45)-SUM(D33:D45) -> -1128.3836 | M45: 230 | N45: 2500 | O45: =I45-D45 -> -85.118443 | P45: =SUM(O33:O45)+M45+N45 -> 1601.6164 | Q45: =L45+M45+N45 -> 1601.6164 | R45: =Q45/K45 -> 0.2396332
B46: 47119 | C46: =C45-E45 -> 270164.62 | D46: =(C46*S$2)/12 -> 783.47739 | E46: =F46-D46 -> 567.52261 | F46: 1351 | I46: =I45 -> 700 | O46: =I46-D46 -> -83.477386
B47: 47150 | C47: =C46-E46 -> 269597.09 | D47: =(C47*S$2)/12 -> 781.83157 | E47: =F47-D47 -> 569.16843 | F47: 1351 | I47: =I46 -> 700 | O47: =I47-D47 -> -81.831571
B48: 47178 | C48: =C47-E47 -> 269027.92 | D48: =(C48*S$2)/12 -> 780.18098 | E48: =F48-D48 -> 570.81902 | F48: 1351 | I48: =I47 -> 700 | O48: =I48-D48 -> -80.180982
B49: 47209 | C49: =C48-E48 -> 268457.11 | D49: =(C49*S$2)/12 -> 778.52561 | E49: =F49-D49 -> 572.47439 | F49: 1351 | I49: =I48 -> 700 | O49: =I49-D49 -> -78.525607
B50: 47239 | C50: =C49-E49 -> 267884.63 | D50: =(C50*S$2)/12 -> 776.86543 | E50: =F50-D50 -> 574.13457 | F50: 1351 | I50: =I49 -> 700 | O50: =I50-D50 -> -76.865432
B51: 47270 | C51: =C50-E50 -> 267310.5 | D51: =(C51*S$2)/12 -> 775.20044 | E51: =F51-D51 -> 575.79956 | F51: 1351 | I51: =I50 -> 700 | O51: =I51-D51 -> -75.200441
B52: 47300 | C52: =C51-E51 -> 266734.7 | D52: =(C52*S$2)/12 -> 773.53062 | E52: =F52-D52 -> 577.46938 | F52: 1351 | I52: =I51 -> 700 | O52: =I52-D52 -> -73.530623
B53: 47331 | C53: =C52-E52 -> 266157.23 | D53: =(C53*S$2)/12 -> 771.85596 | E53: =F53-D53 -> 579.14404 | F53: 1351 | I53: =I52 -> 700 | O53: =I53-D53 -> -71.855961
B54: 47361 | C54: =C53-E53 -> 265578.08 | D54: 0 | E54: 0 | F54: 0 | O54: =D54-G54 -> 0
B55: 47362 | C55: =C54-G54 -> 265578.08 | D55: =(C55*S$2)/12 -> 770.17644 | E55: =F55-D55 -> 580.82356 | F55: 1351 | I55: =I53 -> 700 | O55: =I55-D55 -> -70.176444
B56: 47392 | C56: =C55-E55 -> 264997.26 | D56: =(C56*S$2)/12 -> 768.49206 | E56: =F56-D56 -> 582.50794 | F56: 1351 | I56: =I55 -> 700 | O56: =I56-D56 -> -68.492055
B57: 47423 | C57: =C56-E56 -> 264414.75 | D57: =(C57*S$2)/12 -> 766.80278 | E57: =F57-D57 -> 584.19722 | F57: 1351 | I57: =I55 -> 700 | O57: =I57-D57 -> -66.802782
A58: 4 | B58: 47453 | C58: =C57-E57 -> 263830.56 | D58: =(C58*S$2)/12 -> 765.10861 | E58: =F58-D58 -> 585.89139 | F58: 1351 | I58: 775 | J58: =(I58/$J$2)/0.66 -> 14.67803 | K58: =SUM(E46:E58)+G54 -> 6919.9521 | L58: =SUM(I46:I58)-SUM(D46:D58) -> -817.0479 | M58: 230 | N58: 2500 | O58: =I58-D58 -> 9.8913896 | P58: =SUM(O46:O58)+M58+N58 -> 1912.9521 | Q58: =L58+M58+N58 -> 1912.9521 | R58: =Q58/K58 -> 0.27644008
B59: 47484 | C59: =C58-E58 -> 263244.66 | D59: =(C59*S$2)/12 -> 763.40953 | E59: =F59-D59 -> 587.59047 | F59: 1351 | I59: =I58 -> 775 | O59: =I59-D59 -> 11.590475
B60: 47515 | C60: =C59-E59 -> 262657.07 | D60: =(C60*S$2)/12 -> 761.70551 | E60: =F60-D60 -> 589.29449 | F60: 1351 | I60: =I59 -> 775 | O60: =I60-D60 -> 13.294487
B61: 47543 | C61: =C60-E60 -> 262067.78 | D61: =(C61*S$2)/12 -> 759.99656 | E61: =F61-D61 -> 591.00344 | F61: 1351 | I61: =I60 -> 775 | O61: =I61-D61 -> 15.003441
B62: 47574 | C62: =C61-E61 -> 261476.78 | D62: =(C62*S$2)/12 -> 758.28265 | E62: =F62-D62 -> 592.71735 | F62: 1351 | I62: =I61 -> 775 | O62: =I62-D62 -> 16.717351
B63: 47604 | C63: =C62-E62 -> 260884.06 | D63: =(C63*S$2)/12 -> 756.56377 | E63: =F63-D63 -> 594.43623 | F63: 1351 | I63: =I62 -> 775 | O63: =I63-D63 -> 18.436231
B64: 47635 | C64: =C63-E63 -> 260289.62 | D64: =(C64*S$2)/12 -> 754.8399 | E64: =F64-D64 -> 596.1601 | F64: 1351 | I64: =I63 -> 775 | O64: =I64-D64 -> 20.160096
B65: 47665 | C65: =C64-E64 -> 259693.46 | D65: =(C65*S$2)/12 -> 753.11104 | E65: =F65-D65 -> 597.88896 | F65: 1351 | I65: =I64 -> 775 | O65: =I65-D65 -> 21.888961
B66: 47696 | C66: =C65-E65 -> 259095.57 | D66: =(C66*S$2)/12 -> 751.37716 | E66: =F66-D66 -> 599.62284 | F66: 1351 | I66: =I65 -> 775 | O66: =I66-D66 -> 23.622839
B67: 47726 | C67: =C66-E66 -> 258495.95 | D67: 0 | E67: 0 | F67: 0 | O67: =D67-G67 -> 0
B68: 47727 | C68: =C67-G67 -> 258495.95 | D68: =(C68*S$2)/12 -> 749.63826 | E68: =F68-D68 -> 601.36174 | F68: 1351 | I68: =I66 -> 775 | O68: =I68-D68 -> 25.361745
B69: 47757 | C69: =C68-E68 -> 257894.59 | D69: =(C69*S$2)/12 -> 747.89431 | E69: =F69-D69 -> 603.10569 | F69: 1351 | I69: =I68 -> 775 | O69: =I69-D69 -> 27.105694
B70: 47788 | C70: =C69-E69 -> 257291.48 | D70: =(C70*S$2)/12 -> 746.1453 | E70: =F70-D70 -> 604.8547 | F70: 1351 | I70: =I68 -> 775 | O70: =I70-D70 -> 28.8547
A71: 5 | B71: 47818 | C71: =C70-E70 -> 256686.63 | D71: =(C71*S$2)/12 -> 744.39122 | E71: =F71-D71 -> 606.60878 | F71: 1351 | I71: 775 | J71: =(I71/$J$2)/0.66 -> 14.67803 | K71: =SUM(E59:E71)+G67 -> 7164.6448 | L71: =SUM(I59:I71)-SUM(D59:D71) -> 252.6448 | M71: 230 | N71: 2500 | O71: =I71-D71 -> 30.608779 | P71: =SUM(O59:O71)+M71+N71 -> 2982.6448 | Q71: =L71+M71+N71 -> 2982.6448 | R71: =Q71/K71 -> 0.41630044
B72: 47849 | C72: =C71-E71 -> 256080.02 | D72: =(C72*S$2)/12 -> 742.63206 | E72: =F72-D72 -> 608.36794 | F72: 1351 | I72: =I71 -> 775 | O72: =I72-D72 -> 32.367945
B73: 47880 | C73: =C72-E72 -> 255471.65 | D73: =(C73*S$2)/12 -> 740.86779 | E73: =F73-D73 -> 610.13221 | F73: 1351 | I73: =I72 -> 775 | O73: =I73-D73 -> 34.132212
B74: 47908 | C74: =C73-E73 -> 254861.52 | D74: =(C74*S$2)/12 -> 739.09841 | E74: =F74-D74 -> 611.90159 | F74: 1351 | I74: =I73 -> 775 | O74: =I74-D74 -> 35.901595
B75: 47939 | C75: =C74-E74 -> 254249.62 | D75: =(C75*S$2)/12 -> 737.32389 | E75: =F75-D75 -> 613.67611 | F75: 1351 | I75: =I74 -> 775 | O75: =I75-D75 -> 37.67611
B76: 47969 | C76: =C75-E75 -> 253635.94 | D76: =(C76*S$2)/12 -> 735.54423 | E76: =F76-D76 -> 615.45577 | F76: 1351 | I76: =I75 -> 775 | O76: =I76-D76 -> 39.45577
B77: 48000 | C77: =C76-E76 -> 253020.49 | D77: =(C77*S$2)/12 -> 733.75941 | E77: =F77-D77 -> 617.24059 | F77: 1351 | I77: =I76 -> 775 | O77: =I77-D77 -> 41.240592
B78: 48030 | C78: =C77-E77 -> 252403.24 | D78: =(C78*S$2)/12 -> 731.96941 | E78: =F78-D78 -> 619.03059 | F78: 1351 | I78: =I77 -> 775 | O78: =I78-D78 -> 43.03059
B79: 48061 | C79: =C78-E78 -> 251784.21 | D79: =(C79*S$2)/12 -> 730.17422 | E79: =F79-D79 -> 620.82578 | F79: 1351 | I79: =I78 -> 775 | O79: =I79-D79 -> 44.825778
B80: 48091 | C80: =C79-E79 -> 251163.39 | D80: 0 | E80: 0 | F80: 0 | O80: =D80-G80 -> 0
B81: 48092 | C81: =C80-G80 -> 251163.39 | D81: =(C81*S$2)/12 -> 728.37383 | E81: =F81-D81 -> 622.62617 | F81: 1351 | I81: =I79 -> 775 | O81: =I81-D81 -> 46.626173
B82: 48122 | C82: =C81-E81 -> 250540.76 | D82: =(C82*S$2)/12 -> 726.56821 | E82: =F82-D82 -> 624.43179 | F82: 1351 | I82: =I81 -> 775 | O82: =I82-D82 -> 48.431789
B83: 48153 | C83: =C82-E82 -> 249916.33 | D83: =(C83*S$2)/12 -> 724.75736 | E83: =F83-D83 -> 626.24264 | F83: 1351 | I83: =I81 -> 775 | O83: =I83-D83 -> 50.242641
A84: 6 | B84: 48183 | C84: =C83-E83 -> 249290.09 | D84: =(C84*S$2)/12 -> 722.94126 | E84: =F84-D84 -> 628.05874 | F84: 1351 | I84: 775 | J84: =(I84/$J$2)/0.66 -> 14.67803 | K84: =SUM(E72:E84)+G80 -> 7417.9899 | L84: =SUM(I72:I84)-SUM(D72:D84) -> 505.98994 | M84: 230 | N84: 2500 | O84: =I84-D84 -> 52.058745 | P84: =SUM(O72:O84)+M84+N84 -> 3235.9899 | Q84: =L84+M84+N84 -> 3235.9899 | R84: =Q84/K84 -> 0.43623542
B85: 48214 | C85: =C84-E84 -> 248662.03 | D85: =(C85*S$2)/12 -> 721.11988 | E85: =F85-D85 -> 629.88012 | F85: 1351 | I85: =I84 -> 775 | O85: =I85-D85 -> 53.880115
B86: 48245 | C86: =C85-E85 -> 248032.15 | D86: =(C86*S$2)/12 -> 719.29323 | E86: =F86-D86 -> 631.70677 | F86: 1351 | I86: =I85 -> 775 | O86: =I86-D86 -> 55.706768
B87: 48274 | C87: =C86-E86 -> 247400.44 | D87: =(C87*S$2)/12 -> 717.46128 | E87: =F87-D87 -> 633.53872 | F87: 1351 | I87: =I86 -> 775 | O87: =I87-D87 -> 57.538717
B88: 48305 | C88: =C87-E87 -> 246766.9 | D88: =(C88*S$2)/12 -> 715.62402 | E88: =F88-D88 -> 635.37598 | F88: 1351 | I88: =I87 -> 775 | O88: =I88-D88 -> 59.37598
B89: 48335 | C89: =C88-E88 -> 246131.53 | D89: =(C89*S$2)/12 -> 713.78143 | E89: =F89-D89 -> 637.21857 | F89: 1351 | I89: =I88 -> 775 | O89: =I89-D89 -> 61.21857
B90: 48366 | C90: =C89-E89 -> 245494.31 | D90: =(C90*S$2)/12 -> 711.9335 | E90: =F90-D90 -> 639.0665 | F90: 1351 | I90: =I89 -> 775 | O90: =I90-D90 -> 63.066504
B91: 48396 | C91: =C90-E90 -> 244855.24 | D91: =(C91*S$2)/12 -> 710.0802 | E91: =F91-D91 -> 640.9198 | F91: 1351 | I91: =I90 -> 775 | O91: =I91-D91 -> 64.919797
B92: 48427 | C92: =C91-E91 -> 244214.32 | D92: =(C92*S$2)/12 -> 708.22154 | E92: =F92-D92 -> 642.77846 | F92: 1351 | I92: =I91 -> 775 | O92: =I92-D92 -> 66.778464
B93: 48457 | C93: =C92-E92 -> 243571.54 | D93: 0 | E93: 0 | F93: 0 | O93: =D93-G93 -> 0
B94: 48458 | C94: =C93-G93 -> 243571.54 | D94: =(C94*S$2)/12 -> 706.35748 | E94: =F94-D94 -> 644.64252 | F94: 1351 | I94: =I92 -> 775 | O94: =I94-D94 -> 68.642522
B95: 48488 | C95: =C94-E94 -> 242926.9 | D95: =(C95*S$2)/12 -> 704.48802 | E95: =F95-D95 -> 646.51198 | F95: 1351 | I95: =I94 -> 775 | O95: =I95-D95 -> 70.511985
B96: 48519 | C96: =C95-E95 -> 242280.39 | D96: =(C96*S$2)/12 -> 702.61313 | E96: =F96-D96 -> 648.38687 | F96: 1351 | I96: =I94 -> 775 | O96: =I96-D96 -> 72.38687
A97: 7 | B97: 48549 | C97: =C96-E96 -> 241632 | D97: =(C97*S$2)/12 -> 700.73281 | E97: =F97-D97 -> 650.26719 | F97: 1351 | I97: 775 | J97: =(I97/$J$2)/0.66 -> 14.67803 | K97: =SUM(E85:E97)+G93 -> 7680.2935 | L97: =SUM(I85:I97)-SUM(D85:D97) -> 768.29348 | M97: 230 | N97: 2500 | O97: =I97-D97 -> 74.267192 | P97: =SUM(O85:O97)+M97+N97 -> 3498.2935 | Q97: =L97+M97+N97 -> 3498.2935 | R97: =Q97/K97 -> 0.45548956
B98: 48580 | C98: =C97-E97 -> 240981.74 | D98: =(C98*S$2)/12 -> 698.84703 | E98: =F98-D98 -> 652.15297 | F98: 1351 | I98: =I97 -> 775 | O98: =I98-D98 -> 76.152966
B99: 48611 | C99: =C98-E98 -> 240329.58 | D99: =(C99*S$2)/12 -> 696.95579 | E99: =F99-D99 -> 654.04421 | F99: 1351 | I99: =I98 -> 775 | O99: =I99-D99 -> 78.04421
B100: 48639 | C100: =C99-E99 -> 239675.54 | D100: =(C100*S$2)/12 -> 695.05906 | E100: =F100-D100 -> 655.94094 | F100: 1351 | I100: =I99 -> 775 | O100: =I100-D100 -> 79.940938
...
